Workbook

Sheet Memória de Cálculo
A1: Mês | B1: 45658 | C1: 45689 | D1: 45717 | E1: 45748 | F1: 45778 | G1: 45809 | H1: 45839 | I1: 45870 | J1: 45901 | K1: 45931 | L1: 45962 | M1: 45992
A2: Horas | B2: 744 | C2: =28*24 -> 672 | D2: 744 | E2: 720 | F2: 744 | G2: 720 | H2: 744 | I2: 744 | J2: 720 | K2: 744 | L2: 720 | M2: 744
A4: Metalurgia
A6: Volume de Contratos (MWmédios)
A7: CHESF | B7: 55 | C7: 55 | D7: 55 | E7: 55 | F7: 55 | G7: 55 | H7: 55 | I7: 55 | J7: 55 | K7: 55 | L7: 55 | M7: 55
A8: AES | B8: 80 | C8: 80 | D8: 80 | E8: 80 | F8: 80 | G8: 80 | H8: 80 | I8: 80 | J8: 80 | K8: 80 | L8: 80 | M8: 80
A9: CPFL (Metalurgia) | B9: 25 | C9: 25 | D9: 25 | E9: 25 | F9: 25 | G9: 25 | H9: 25 | I9: 25 | J9: 25 | K9: 25 | L9: 25 | M9: 25
A10: AUREN (APE) | B10: 35 | C10: 35 | D10: 35 | E10: 35 | F10: 35 | G10: 35 | H10: 35 | I10: 35 | J10: 35 | K10: 35 | L10: 35 | M10: 35
A11: Proinfa | B11: 3.9187 | C11: 3.9187 | D11: 3.9187 | E11: 3.9187 | F11: 3.9187 | G11: 3.9187 | H11: 3.9187 | I11: 3.9187 | J11: 3.9187 | K11: 3.9187 | L11: 3.9187 | M11: 3.9187
A13: Volume de Contratos (MWh)
A14: CHESF | B14: =B2*B7 -> 40920 | C14: =C2*C7 -> 36960 | D14: =D2*D7 -> 40920 | E14: =E2*E7 -> 39600 | F14: =F2*F7 -> 40920 | G14: =G2*G7 -> 39600 | H14: =H2*H7 -> 40920 | I14: =I2*I7 -> 40920 | ... M14: =M2*M7 -> 40920
A15: AES | B15: =B8*B2 -> 59520 | C15: =C8*C2 -> 53760 | D15: =D8*D2 -> 59520 | E15: =E8*E2 -> 57600 | F15: =F8*F2 -> 59520 | G15: =G8*G2 -> 57600 | H15: =H8*H2 -> 59520 | I15: =I8*I2 -> 59520 | ... M15: =M8*M2 -> 59520
A16: CPFL (Metalurgia) | B16: =B2*B9 -> 18600 | C16: =C2*C9 -> 16800 | D16: =D2*D9 -> 18600 | E16: =E2*E9 -> 18000 | F16: =F2*F9 -> 18600 | G16: =G2*G9 -> 18000 | H16: =H2*H9 -> 18600 | I16: =I2*I9 -> 18600 | ... M16: =M2*M9 -> 18600
A17: AUREN (APE) | B17: =B2*B10 -> 26040 | C17: =C2*C10 -> 23520 | D17: =D2*D10 -> 26040 | E17: =E2*E10 -> 25200 | F17: =F2*F10 -> 26040 | G17: =G2*G10 -> 25200 | H17: =H2*H10 -> 26040 | I17: =I2*I10 -> 26040 | ... M17: =M2*M10 -> 26040
A18: Proinfa | B18: =B2*B11 -> 2915.5128 | C18: =C2*C11 -> 2633.3664 | D18: =D2*D11 -> 2915.5128 | E18: =E2*E11 -> 2821.464 | F18: =F2*F11 -> 2915.5128 | G18: =G2*G11 -> 2821.464 | H18: =H2*H11 -> 2915.5128 | I18: =I2*I11 -> 2915.5128 | ... M18: =M2*M11 -> 2915.5128
B20: =SUM(B15:B17) -> 104160 | C20: =SUM(C15:C17) -> 94080 | D20: =SUM(D15:D17) -> 104160 | E20: =SUM(E15:E17) -> 100800 | F20: =SUM(F15:F17) -> 104160 | G20: =SUM(G15:G17) -> 100800 | H20: =SUM(H15:H17) -> 104160 | I20: =SUM(I15:I17) -> 104160 | ... M20: =SUM(M15:M17) -> 104160
A21: Preços de Consumo (Posto Fábrica)
A22: CHESF | B22: =Preços!$I$5/(0.97*'Energia Aux - Met'!$S$71)+B45 -> 196.30408 | C22: =Preços!$I$5/(0.97*'Energia Aux - Met'!$S$71)+C45 -> 196.36728 | D22: =Preços!$I$5/(0.97*'Energia Aux - Met'!$S$71)+D45 -> 196.17878 | E22: =Preços!$I$5/(0.97*'Energia Aux - Met'!$S$71)+E45 -> 196.66994 | F22: =Preços!$I$5/(0.97*'Energia Aux - Met'!$S$71)+F45 -> 197.13329 | G22: =Preços!$I$5/(0.97*'Energia Aux - Met'!$S$71)+G45 -> 197.59369 | H22: =Preços!$I$5/(0.97*'Energia Aux - Met'!$S$71)+H45 -> 197.45132 | I22: =Preços!$I$5/(0.97*'Energia Aux - Met'!$S$71)+I45 -> 198.96971 | ... M22: =Preços!$I$5/(0.97*'Energia Aux - Met'!$S$71)+M45 -> 198.78871
A23: Médio Demais Contratos | B23: =SUMPRODUCT(B15:B18,B24:B27)/(SUM(B15:B18)*0.97*'Energia Aux - Met'!$S$71)+B45 -> 241.06909 | C23: =SUMPRODUCT(C15:C18,C24:C27)/(SUM(C15:C18)*0.97*'Energia Aux - Met'!$S$71)+C45 -> 241.13229 | D23: =SUMPRODUCT(D15:D18,D24:D27)/(SUM(D15:D18)*0.97*'Energia Aux - Met'!$S$71)+D45 -> 240.94378 | E23: =SUMPRODUCT(E15:E18,E24:E27)/(SUM(E15:E18)*0.97*'Energia Aux - Met'!$S$71)+E45 -> 241.43495 | F23: =SUMPRODUCT(F15:F18,F24:F27)/(SUM(F15:F18)*0.97*'Energia Aux - Met'!$S$71)+F45 -> 241.89829 | G23: =SUMPRODUCT(G15:G18,G24:G27)/(SUM(G15:G18)*0.97*'Energia Aux - Met'!$S$71)+G45 -> 242.35869 | H23: =SUMPRODUCT(H15:H18,H24:H27)/(SUM(H15:H18)*0.97*'Energia Aux - Met'!$S$71)+H45 -> 242.21632 | I23: =SUMPRODUCT(I15:I18,I24:I27)/(SUM(I15:I18)*0.97*'Energia Aux - Met'!$S$71)+I45 -> 243.73471 | ... M23: =SUMPRODUCT(M15:M18,M24:M27)/(SUM(M15:M18)*0.97*'Energia Aux - Met'!$S$71)+M45 -> 243.55372
A24: AES | B24: =Preços!$I$6 -> 124.58484 | C24: =Preços!$I$6 -> 124.58484 | D24: =Preços!$I$6 -> 124.58484 | E24: =Preços!$I$6 -> 124.58484 | F24: =Preços!$I$6 -> 124.58484 | G24: =Preços!$I$6 -> 124.58484 | H24: =Preços!$I$6 -> 124.58484 | I24: =Preços!$I$6 -> 124.58484 | ... M24: =Preços!$I$6 -> 124.58484
A25: CPFL (Metalurgia) | B25: =Preços!$I$7 -> 203.97232 | C25: =Preços!$I$7 -> 203.97232 | D25: =Preços!$I$7 -> 203.97232 | E25: =Preços!$I$7 -> 203.97232 | F25: =Preços!$I$7 -> 203.97232 | G25: =Preços!$I$7 -> 203.97232 | H25: =Preços!$I$7 -> 203.97232 | I25: =Preços!$I$7 -> 203.97232 | ... M25: =Preços!$I$7 -> 203.97232
A26: AUREN (APE) | B26: =Preços!$I$8 -> 189.76424 | C26: =Preços!$I$8 -> 189.76424 | D26: =Preços!$I$8 -> 189.76424 | E26: =Preços!$I$8 -> 189.76424 | F26: =Preços!$I$8 -> 189.76424 | G26: =Preços!$I$8 -> 189.76424 | H26: =Preços!$I$8 -> 189.76424 | I26: =Preços!$I$8 -> 189.76424 | ... M26: =Preços!$I$8 -> 189.76424
A27: Proinfa | B27: 0 | C27: 0 | D27: 0 | E27: 0 | F27: 0 | G27: 0 | H27: 0 | I27: 0 | J27: 0 | K27: 0 | L27: 0 | M27: 0
A29: Encargos (R$/MWh) - Sem APE
A30: Preço transmissao -TUST fio | B30: 26.365521 | C30: 26.434691 | D30: 26.22803 | E30: 26.764505 | F30: 27.272461 | G30: 27.777756 | H30: 27.625243 | I30: 29.286289 | J30: 29.091922 | K30: 29.091922 | L30: 29.091922 | M30: 29.091922
A31: Preço Conexão | B31: 0.10853278 | C31: 0.10865003 | D31: 0.1086236 | E31: 0.11050844 | F31: 0.1105873 | G31: 0.11014842 | H31: 0.10686849 | I31: 0.11034446 | J31: 0.1066183 | K31: 0.1066183 | L31: 0.1066183 | M31: 0.1066183
A32: CDE | B32: 27.08011 | C32: 27.08011 | D32: 27.08011 | E32: 27.08011 | F32: 27.08011 | G32: 27.08011 | H32: 27.08011 | I32: 27.08011 | J32: 27.08011 | K32: 27.08011 | L32: 27.08011 | M32: 27.08011
A33: TUST PROINFA | B33: 9.351405 | C33: 9.351405 | D33: 9.351405 | E33: 9.351405 | F33: 9.351405 | G33: 9.351405 | H33: 9.351405 | I33: 9.351405 | J33: 9.351405 | K33: 9.351405 | L33: 9.351405 | M33: 9.351405
A34: ESS | B34: 0.5615427 | C34: 0.5615427 | D34: 0.5615427 | E34: 0.5615427 | F34: 0.5615427 | G34: 0.5615427 | H34: 0.5615427 | I34: 0.5615427 | J34: 0.5615427 | K34: 0.5615427 | L34: 0.5615427 | M34: 0.5615427
A35: EER | B35: 27.767713 | C35: 27.767713 | D35: 27.767713 | E35: 27.767713 | F35: 27.767713 | G35: 27.767713 | H35: 27.767713 | I35: 27.767713 | J35: 27.767713 | K35: 27.767713 | L35: 27.767713 | M35: 27.767713
A36: Total Encargos | B36: =SUM(B30:B35) -> 91.234825 | C36: =SUM(C30:C35) -> 91.304112 | D36: =SUM(D30:D35) -> 91.097425 | E36: =SUM(E30:E35) -> 91.635785 | F36: =SUM(F30:F35) -> 92.14382 | G36: =SUM(G30:G35) -> 92.648675 | H36: =SUM(H30:H35) -> 92.492883 | I36: =SUM(I30:I35) -> 94.157405 | ... M36: =SUM(M30:M35) -> 93.959311
A38: Encargos (R$/MWh) - Com APE
A39: Preço transmissao -TUST fio | B39: =((SUM(B14:B16,B18)*B30)+(B17*B30/2))/SUM(B14:B18) -> 24.045998 | C39: =((SUM(C14:C16,C18)*C30)+(C17*C30/2))/SUM(C14:C18) -> 24.109082 | D39: =((SUM(D14:D16,D18)*D30)+(D17*D30/2))/SUM(D14:D18) -> 23.920602 | E39: =((SUM(E14:E16,E18)*E30)+(E17*E30/2))/SUM(E14:E18) -> 24.409881 | F39: =((SUM(F14:F16,F18)*F30)+(F17*F30/2))/SUM(F14:F18) -> 24.873149 | G39: =((SUM(G14:G16,G18)*G30)+(G17*G30/2))/SUM(G14:G18) -> 25.33399 | H39: =((SUM(H14:H16,H18)*H30)+(H17*H30/2))/SUM(H14:H18) -> 25.194895 | I39: =((SUM(I14:I16,I18)*I30)+(I17*I30/2))/SUM(I14:I18) -> 26.709809 | ... M39: =((SUM(M14:M16,M18)*M30)+(M17*M30/2))/SUM(M14:M18) -> 26.532541
A40: Preço Conexão | B40: =B31 -> 0.10853278 | C40: =C31 -> 0.10865003 | D40: =D31 -> 0.1086236 | E40: =E31 -> 0.11050844 | F40: =F31 -> 0.1105873 | G40: =G31 -> 0.11014842 | H40: =H31 -> 0.10686849 | I40: =I31 -> 0.11034446 | ... M40: =M31 -> 0.1066183
A41: CDE | B41: =((SUM(B$14:B$16,B$18)*B$32)+(B$17*0))/SUM(B$14:B$18) -> 22.31533 | C41: =((SUM(C$14:C$16,C$18)*C$32)+(C$17*0))/SUM(C$14:C$18) -> 22.31533 | D41: =((SUM(D$14:D$16,D$18)*D$32)+(D$17*0))/SUM(D$14:D$18) -> 22.31533 | E41: =((SUM(E$14:E$16,E$18)*E$32)+(E$17*0))/SUM(E$14:E$18) -> 22.31533 | F41: =((SUM(F$14:F$16,F$18)*F$32)+(F$17*0))/SUM(F$14:F$18) -> 22.31533 | G41: =((SUM(G$14:G$16,G$18)*G$32)+(G$17*0))/SUM(G$14:G$18) -> 22.31533 | H41: =((SUM(H$14:H$16,H$18)*H$32)+(H$17*0))/SUM(H$14:H$18) -> 22.31533 | I41: =((SUM(I$14:I$16,I$18)*I$32)+(I$17*0))/SUM(I$14:I$18) -> 22.31533 | ... M41: =((SUM(M$14:M$16,M$18)*M$32)+(M$17*0))/SUM(M$14:M$18) -> 22.31533
A42: TUST PROINFA | B42: =((SUM(B$14:B$16,B$18)*B$33)+(B$17*0))/SUM(B$14:B$18) -> 7.7060133 | C42: =((SUM(C$14:C$16,C$18)*C$33)+(C$17*0))/SUM(C$14:C$18) -> 7.7060133 | D42: =((SUM(D$14:D$16,D$18)*D$33)+(D$17*0))/SUM(D$14:D$18) -> 7.7060133 | E42: =((SUM(E$14:E$16,E$18)*E$33)+(E$17*0))/SUM(E$14:E$18) -> 7.7060133 | F42: =((SUM(F$14:F$16,F$18)*F$33)+(F$17*0))/SUM(F$14:F$18) -> 7.7060133 | G42: =((SUM(G$14:G$16,G$18)*G$33)+(G$17*0))/SUM(G$14:G$18) -> 7.7060133 | H42: =((SUM(H$14:H$16,H$18)*H$33)+(H$17*0))/SUM(H$14:H$18) -> 7.7060133 | I42: =((SUM(I$14:I$16,I$18)*I$33)+(I$17*0))/SUM(I$14:I$18) -> 7.7060133 | ... M42: =((SUM(M$14:M$16,M$18)*M$33)+(M$17*0))/SUM(M$14:M$18) -> 7.7060133
A43: ESS | B43: =((SUM(B$14:B$16,B$18)*B$34)+(B$17*0))/SUM(B$14:B$18) -> 0.46273854 | C43: =((SUM(C$14:C$16,C$18)*C$34)+(C$17*0))/SUM(C$14:C$18) -> 0.46273854 | D43: =((SUM(D$14:D$16,D$18)*D$34)+(D$17*0))/SUM(D$14:D$18) -> 0.46273854 | E43: =((SUM(E$14:E$16,E$18)*E$34)+(E$17*0))/SUM(E$14:E$18) -> 0.46273854 | F43: =((SUM(F$14:F$16,F$18)*F$34)+(F$17*0))/SUM(F$14:F$18) -> 0.46273854 | G43: =((SUM(G$14:G$16,G$18)*G$34)+(G$17*0))/SUM(G$14:G$18) -> 0.46273854 | H43: =((SUM(H$14:H$16,H$18)*H$34)+(H$17*0))/SUM(H$14:H$18) -> 0.46273854 | I43: =((SUM(I$14:I$16,I$18)*I$34)+(I$17*0))/SUM(I$14:I$18) -> 0.46273854 | ... M43: =((SUM(M$14:M$16,M$18)*M$34)+(M$17*0))/SUM(M$14:M$18) -> 0.46273854
A44: EER | B44: =((SUM(B$14:B$16,B$18)*B$35)+(B$17*0))/SUM(B$14:B$18) -> 22.881949 | C44: =((SUM(C$14:C$16,C$18)*C$35)+(C$17*0))/SUM(C$14:C$18) -> 22.881949 | D44: =((SUM(D$14:D$16,D$18)*D$35)+(D$17*0))/SUM(D$14:D$18) -> 22.881949 | E44: =((SUM(E$14:E$16,E$18)*E$35)+(E$17*0))/SUM(E$14:E$18) -> 22.881949 | F44: =((SUM(F$14:F$16,F$18)*F$35)+(F$17*0))/SUM(F$14:F$18) -> 22.881949 | G44: =((SUM(G$14:G$16,G$18)*G$35)+(G$17*0))/SUM(G$14:G$18) -> 22.881949 | H44: =((SUM(H$14:H$16,H$18)*H$35)+(H$17*0))/SUM(H$14:H$18) -> 22.881949 | I44: =((SUM(I$14:I$16,I$18)*I$35)+(I$17*0))/SUM(I$14:I$18) -> 22.881949 | ... M44: =((SUM(M$14:M$16,M$18)*M$35)+(M$17*0))/SUM(M$14:M$18) -> 22.881949
A45: Total Encargos | B45: =SUM(B39:B44) -> 77.520561 | C45: =SUM(C39:C44) -> 77.583763 | D45: =SUM(D39:D44) -> 77.395257 | E45: =SUM(E39:E44) -> 77.88642 | F45: =SUM(F39:F44) -> 78.349767 | G45: =SUM(G39:G44) -> 78.810169 | H45: =SUM(H39:H44) -> 78.667794 | I45: =SUM(I39:I44) -> 80.186184 | ... M45: =SUM(M39:M44) -> 80.00519
A48: Preços do Porftólio para Cessão (R$/MWh) | B48: =SUMPRODUCT(B24:B26,B15:B17)/SUM(B15:B17)/0.9075 -> 170.86063 | C48: =SUMPRODUCT(C24:C26,C15:C17)/SUM(C15:C17)/0.9075 -> 170.86063 | D48: =SUMPRODUCT(D24:D26,D15:D17)/SUM(D15:D17)/0.9075 -> 170.86063 | E48: =SUMPRODUCT(E24:E26,E15:E17)/SUM(E15:E17)/0.9075 -> 170.86063 | F48: =SUMPRODUCT(F24:F26,F15:F17)/SUM(F15:F17)/0.9075 -> 170.86063 | G48: =SUMPRODUCT(G24:G26,G15:G17)/SUM(G15:G17)/0.9075 -> 170.86063 | H48: =SUMPRODUCT(H24:H26,H15:H17)/SUM(H15:H17)/0.9075 -> 170.86063 | I48: =SUMPRODUCT(I24:I26,I15:I17)/SUM(I15:I17)/0.9075 -> 170.86063 | ... M48: =SUMPRODUCT(M24:M26,M15:M17)/SUM(M15:M17)/0.9075 -> 170.86063
A49: Preço de Energia no MCP(R$/MWh) | B49: ='Curva de Preços SPOT'!B9 -> 175.43 | C49: ='Curva de Preços SPOT'!C9 -> 175.43 | D49: ='Curva de Preços SPOT'!D9 -> 175.43 | E49: ='Curva de Preços SPOT'!E9 -> 175.43 | F49: ='Curva de Preços SPOT'!F9 -> 175.43 | G49: ='Curva de Preços SPOT'!G9 -> 175.43 | H49: ='Curva de Preços SPOT'!H9 -> 175.43 | I49: ='Curva de Preços SPOT'!I9 -> 175.43 | ... M49: ='Curva de Preços SPOT'!M9 -> 175.43
A50: Preços de Consumo Energia MCP (R$/MWh) | B50: =(B49*0.9075)/0.97+(SUM(B15:B16)*B36+B17*(B39/B30/2+B31))/SUM(B15:B17) -> 232.69378 | C50: =(C49*0.9075)/0.97+(SUM(C15:C16)*C36+C17*(C39/C30/2+C31))/SUM(C15:C17) -> 232.74577 | D50: =(D49*0.9075)/0.97+(SUM(D15:D16)*D36+D17*(D39/D30/2+D31))/SUM(D15:D17) -> 232.59075 | E50: =(E49*0.9075)/0.97+(SUM(E15:E16)*E36+E17*(E39/E30/2+E31))/SUM(E15:E17) -> 232.99499 | F50: =(F49*0.9075)/0.97+(SUM(F15:F16)*F36+F17*(F39/F30/2+F31))/SUM(F15:F17) -> 233.37604 | G50: =(G49*0.9075)/0.97+(SUM(G15:G16)*G36+G17*(G39/G30/2+G31))/SUM(G15:G17) -> 233.75457 | H50: =(H49*0.9075)/0.97+(SUM(H15:H16)*H36+H17*(H39/H30/2+H31))/SUM(H15:H17) -> 233.6369 | I50: =(I49*0.9075)/0.97+(SUM(I15:I16)*I36+I17*(I39/I30/2+I31))/SUM(I15:I17) -> 234.88616 | ... M50: =(M49*0.9075)/0.97+(SUM(M15:M16)*M36+M17*(M39/M30/2+M31))/SUM(M15:M17) -> 234.73666
A52: Mineração Ipueira
A54: Volume de Contratos (MWmédios)
A55: Prime Energy | B55: 0 | C55: 0 | D55: 0 | E55: 0 | F55: 0 | G55: 0 | H55: 0 | I55: 0 | J55: 0 | K55: 0 | L55: 0 | M55: 0
A56: CPFL | B56: 5 | C56: 5 | D56: 5 | E56: 5 | F56: 5 | G56: 5 | H56: 5 | I56: 5 | J56: 5 | K56: 5 | L56: 5 | M56: 5
A57: Proinfa | B57: 0.0965 | C57: 0.0965 | D57: 0.0965 | E57: 0.0965 | F57: 0.0965 | G57: 0.0965 | H57: 0.0965 | I57: 0.0965 | J57: 0.0965 | K57: 0.0965 | L57: 0.0965 | M57: 0.0965
A59: Volume de Contratos (MWh)
A60: Prime Energy | B60: =B55*B2 -> 0 | C60: =C55*C2 -> 0 | D60: =D55*D2 -> 0 | E60: =E55*E2 -> 0 | F60: =F55*F2 -> 0 | G60: =G55*G2 -> 0 | H60: =H55*H2 -> 0 | I60: =I55*I2 -> 0 | ... M60: =M55*M2 -> 0
A61: CPFL | B61: =B56*B2 -> 3720 | C61: =C56*C2 -> 3360 | D61: =D56*D2 -> 3720 | E61: =E56*E2 -> 3600 | F61: =F56*F2 -> 3720 | G61: =G56*G2 -> 3600 | H61: =H56*H2 -> 3720 | I61: =I56*I2 -> 3720 | ... M61: =M56*M2 -> 3720
A62: Proinfa | B62: =B57*B2 -> 71.796 | C62: =C57*C2 -> 64.848 | D62: =D57*D2 -> 71.796 | E62: =E57*E2 -> 69.48 | F62: =F57*F2 -> 71.796 | G62: =G57*G2 -> 69.48 | H62: =H57*H2 -> 71.796 | I62: =I57*I2 -> 71.796 | ... M62: =M57*M2 -> 71.796
A64: Preços de Consumo (Posto Fábrica)
A65: Média dos Contratos (R$/MWh) | B65: =SUMPRODUCT(B66:B68,B60:B62)/(SUM(B60:B62)*0.97)+B73 -> 361.28454 | C65: =SUMPRODUCT(C66:C68,C60:C62)/(SUM(C60:C62)*0.97)+C73 -> 372.45047 | D65: =SUMPRODUCT(D66:D68,D60:D62)/(SUM(D60:D62)*0.97)+D73 -> 361.28454 | E65: =SUMPRODUCT(E66:E68,E60:E62)/(SUM(E60:E62)*0.97)+E73 -> 352.50978 | F65: =SUMPRODUCT(F66:F68,F60:F62)/(SUM(F60:F62)*0.97)+F73 -> 349.53782 | G65: =SUMPRODUCT(G66:G68,G60:G62)/(SUM(G60:G62)*0.97)+G73 -> 352.50978 | H65: =SUMPRODUCT(H66:H68,H60:H62)/(SUM(H60:H62)*0.97)+H73 -> 349.53782 | I65: =SUMPRODUCT(I66:I68,I60:I62)/(SUM(I60:I62)*0.97)+I73 -> 349.53782 | ... M65: =SUMPRODUCT(M66:M68,M60:M62)/(SUM(M60:M62)*0.97)+M73 -> 349.53782
A66: Prime
A67: CPFL | B67: =B25 -> 203.97232 | C67: =C25 -> 203.97232 | D67: =D25 -> 203.97232 | E67: =E25 -> 203.97232 | F67: =F25 -> 203.97232 | G67: =G25 -> 203.97232 | H67: =H25 -> 203.97232 | I67: =I25 -> 203.97232 | ... M67: =M25 -> 203.97232
A68: Proinfa | B68: 0 | C68: 0 | D68: 0 | E68: 0 | F68: 0 | G68: 0 | H68: 0 | I68: 0 | J68: 0 | K68: 0 | L68: 0 | M68: 0
A70: Encargos (R$/MWh)
A71: TUSD Fio | B71: ='Encargos Mineração'!C24 -> 104.21538 | C71: ='Encargos Mineração'!D24 -> 115.38131 | D71: ='Encargos Mineração'!E24 -> 104.21538 | E71: ='Encargos Mineração'!F24 -> 92.130611 | F71: ='Encargos Mineração'!G24 -> 89.158656 | G71: ='Encargos Mineração'!H24 -> 92.130611 | H71: ='Encargos Mineração'!I24 -> 89.158656 | I71: ='Encargos Mineração'!J24 -> 89.158656 | ... M71: ='Encargos Mineração'!N24 -> 89.158656
A72: TUSD Encargos | B72: ='Encargos Mineração'!C25 -> 50.77 | C72: ='Encargos Mineração'!D25 -> 50.77 | D72: ='Encargos Mineração'!E25 -> 50.77 | E72: ='Encargos Mineração'!F25 -> 54.08 | F72: ='Encargos Mineração'!G25 -> 54.08 | G72: ='Encargos Mineração'!H25 -> 54.08 | H72: ='Encargos Mineração'!I25 -> 54.08 | I72: ='Encargos Mineração'!J25 -> 54.08 | ... M72: ='Encargos Mineração'!N25 -> 54.08
A73: Total Encargos Mineração com Desconto % | B73: =B71*(1-B60/SUM(B60:B62)*0.5)+B72 -> 154.98538 | C73: =C71*(1-C60/SUM(C60:C62)*0.5)+C72 -> 166.15131 | D73: =D71*(1-D60/SUM(D60:D62)*0.5)+D72 -> 154.98538 | E73: =E71*(1-E60/SUM(E60:E62)*0.5)+E72 -> 146.21061 | F73: =F71*(1-F60/SUM(F60:F62)*0.5)+F72 -> 143.23866 | G73: =G71*(1-G60/SUM(G60:G62)*0.5)+G72 -> 146.21061 | H73: =H71*(1-H60/SUM(H60:H62)*0.5)+H72 -> 143.23866 | I73: =I71*(1-I60/SUM(I60:I62)*0.5)+I72 -> 143.23866 | ... M73: =M71*(1-M60/SUM(M60:M62)*0.5)+M72 -> 143.23866
A75: Preços do Porftólio para Cessão (R$/MWh) | B75: =SUMPRODUCT(B66:B67,B60:B61)/SUM(B60:B61)/0.9075 -> 224.76288 | C75: =SUMPRODUCT(C66:C67,C60:C61)/SUM(C60:C61)/0.9075 -> 224.76288 | D75: =SUMPRODUCT(D66:D67,D60:D61)/SUM(D60:D61)/0.9075 -> 224.76288 | E75: =SUMPRODUCT(E66:E67,E60:E61)/SUM(E60:E61)/0.9075 -> 224.76288 | F75: =SUMPRODUCT(F66:F67,F60:F61)/SUM(F60:F61)/0.9075 -> 224.76288 | G75: =SUMPRODUCT(G66:G67,G60:G61)/SUM(G60:G61)/0.9075 -> 224.76288 | H75: =SUMPRODUCT(H66:H67,H60:H61)/SUM(H60:H61)/0.9075 -> 224.76288 | I75: =SUMPRODUCT(I66:I67,I60:I61)/SUM(I60:I61)/0.9075 -> 224.76288 | ... M75: =SUMPRODUCT(M66:M67,M60:M61)/SUM(M60:M61)/0.9075 -> 224.76288
A76: Preço de Energia no MCP(R$/MWh) - Convencional | B76: ='Curva de Preços SPOT'!B9 -> 175.43 | C76: ='Curva de Preços SPOT'!C9 -> 175.43 | D76: ='Curva de Preços SPOT'!D9 -> 175.43 | E76: ='Curva de Preços SPOT'!E9 -> 175.43 | F76: ='Curva de Preços SPOT'!F9 -> 175.43 | G76: ='Curva de Preços SPOT'!G9 -> 175.43 | H76: ='Curva de Preços SPOT'!H9 -> 175.43 | I76: ='Curva de Preços SPOT'!I9 -> 175.43 | ... M76: ='Curva de Preços SPOT'!M9 -> 175.43
A77: Preços de Consumo Energia MCP (R$/MWh) | B77: =B76*0.9075+B73 -> 314.1881 | C77: =C76*0.9075+C73 -> 325.35403 | D77: =D76*0.9075+D73 -> 314.1881 | E77: =E76*0.9075+E73 -> 305.41334 | F77: =F76*0.9075+F73 -> 302.44138 | G77: =G76*0.9075+G73 -> 305.41334 | H77: =H76*0.9075+H73 -> 302.44138 | I77: =I76*0.9075+I73 -> 302.44138 | ... M77: =M76*0.9075+M73 -> 302.44138
A79: Premissas:
A80: Reajuste dos contratos de energia conforme contrato - índice de Correção IPCA estimativa Relatório Focus BACEN 28/06/2024 = 4% para 2025
A82: Encargos Setoriais considerando os Benefícios de APE na sua proporção de energia do Portfólio
A83: Encargos Setoriais Mineração IPUEIRA - Até Março resolução homologatória ANEEL 3320 de abril de 2024 e de Abril em diante estimativa ABRACE.
A84: Valor energia Spot: Curva de preços BBCE de 01/07/2024
A85: Proinfa: Média dos valores recebidos em 2024 até Jun

Sheet Montantes
B2: Montantes
C4: Energia para Consumo | D4: JAN | E4: FEV | F4: MAR | G4: ABR | H4: MAI | I4: JUN | J4: JUL | K4: AGO | L4: SET | M4: OUT | N4: NOV | O4: DEZ
B5: Metalurgia | C5: CHESF | D5: ='Memória de Cálculo'!B7 -> 55 | E5: ='Memória de Cálculo'!C7 -> 55 | F5: ='Memória de Cálculo'!D7 -> 55 | G5: ='Memória de Cálculo'!E7 -> 55 | H5: ='Memória de Cálculo'!F7 -> 55 | I5: ='Memória de Cálculo'!G7 -> 55 | J5: ='Memória de Cálculo'!H7 -> 55 | K5: ='Memória de Cálculo'!I7 -> 55 | ... O5: ='Memória de Cálculo'!M7 -> 55
C6: Desc. Perdas | D6: =D5*0.97 -> 53.35 | E6: =E5*0.97 -> 53.35 | F6: =F5*0.97 -> 53.35 | G6: =G5*0.97 -> 53.35 | H6: =H5*0.97 -> 53.35 | I6: =I5*0.97 -> 53.35 | J6: =J5*0.97 -> 53.35 | K6: =K5*0.97 -> 53.35 | ... O6: =O5*0.97 -> 53.35
C7: Desc. Auxiliar | D7: =D6*(1-'Energia Aux - Met'!$T$71) -> 50.724246 | E7: =E6*(1-'Energia Aux - Met'!$T$71) -> 50.724246 | F7: =F6*(1-'Energia Aux - Met'!$T$71) -> 50.724246 | G7: =G6*(1-'Energia Aux - Met'!$T$71) -> 50.724246 | H7: =H6*(1-'Energia Aux - Met'!$T$71) -> 50.724246 | I7: =I6*(1-'Energia Aux - Met'!$T$71) -> 50.724246 | J7: =J6*(1-'Energia Aux - Met'!$T$71) -> 50.724246 | K7: =K6*(1-'Energia Aux - Met'!$T$71) -> 50.724246 | ... O7: =O6*(1-'Energia Aux - Met'!$T$71) -> 50.724246
C8: ML | D8: ='Memória de Cálculo'!B8+'Memória de Cálculo'!B9+'Memória de Cálculo'!B10+'Memória de Cálculo'!B11 -> 143.9187 | E8: ='Memória de Cálculo'!C8+'Memória de Cálculo'!C9+'Memória de Cálculo'!C10+'Memória de Cálculo'!C11 -> 143.9187 | F8: ='Memória de Cálculo'!D8+'Memória de Cálculo'!D9+'Memória de Cálculo'!D10+'Memória de Cálculo'!D11 -> 143.9187 | G8: ='Memória de Cálculo'!E8+'Memória de Cálculo'!E9+'Memória de Cálculo'!E10+'Memória de Cálculo'!E11 -> 143.9187 | H8: ='Memória de Cálculo'!F8+'Memória de Cálculo'!F9+'Memória de Cálculo'!F10+'Memória de Cálculo'!F11 -> 143.9187 | I8: ='Memória de Cálculo'!G8+'Memória de Cálculo'!G9+'Memória de Cálculo'!G10+'Memória de Cálculo'!G11 -> 143.9187 | J8: ='Memória de Cálculo'!H8+'Memória de Cálculo'!H9+'Memória de Cálculo'!H10+'Memória de Cálculo'!H11 -> 143.9187 | K8: ='Memória de Cálculo'!I8+'Memória de Cálculo'!I9+'Memória de Cálculo'!I10+'Memória de Cálculo'!I11 -> 143.9187 | ... O8: ='Memória de Cálculo'!M8+'Memória de Cálculo'!M9+'Memória de Cálculo'!M10+'Memória de Cálculo'!M11 -> 143.9187
C9: Desc. Perdas | D9: =D8*0.97 -> 139.60114 | E9: =E8*0.97 -> 139.60114 | F9: =F8*0.97 -> 139.60114 | G9: =G8*0.97 -> 139.60114 | H9: =H8*0.97 -> 139.60114 | I9: =I8*0.97 -> 139.60114 | J9: =J8*0.97 -> 139.60114 | K9: =K8*0.97 -> 139.60114 | ... O9: =O8*0.97 -> 139.60114
C10: Desc. Auxiliar | D10: =D9*(1-'Energia Aux - Met'!$T$71) -> 132.73032 | E10: =E9*(1-'Energia Aux - Met'!$T$71) -> 132.73032 | F10: =F9*(1-'Energia Aux - Met'!$T$71) -> 132.73032 | G10: =G9*(1-'Energia Aux - Met'!$T$71) -> 132.73032 | H10: =H9*(1-'Energia Aux - Met'!$T$71) -> 132.73032 | I10: =I9*(1-'Energia Aux - Met'!$T$71) -> 132.73032 | J10: =J9*(1-'Energia Aux - Met'!$T$71) -> 132.73032 | K10: =K9*(1-'Energia Aux - Met'!$T$71) -> 132.73032 | ... O10: =O9*(1-'Energia Aux - Met'!$T$71) -> 132.73032
B12: IPUEIRA | C12: PRIME | D12: =('Memória de Cálculo'!B55) -> 0 | E12: =('Memória de Cálculo'!C55) -> 0 | F12: =('Memória de Cálculo'!D55) -> 0 | G12: =('Memória de Cálculo'!E55) -> 0 | H12: =('Memória de Cálculo'!F55) -> 0 | I12: =('Memória de Cálculo'!G55) -> 0 | J12: =('Memória de Cálculo'!H55) -> 0 | K12: =('Memória de Cálculo'!I55) -> 0 | ... O12: =('Memória de Cálculo'!M55) -> 0
C13: CPFL | D13: =('Memória de Cálculo'!B56) -> 5 | E13: =('Memória de Cálculo'!C56) -> 5 | F13: =('Memória de Cálculo'!D56) -> 5 | G13: =('Memória de Cálculo'!E56) -> 5 | H13: =('Memória de Cálculo'!F56) -> 5 | I13: =('Memória de Cálculo'!G56) -> 5 | J13: =('Memória de Cálculo'!H56) -> 5 | K13: =('Memória de Cálculo'!I56) -> 5 | ... O13: =('Memória de Cálculo'!M56) -> 5
C14: PROINFA | D14: =('Memória de Cálculo'!B57) -> 0.0965 | E14: =('Memória de Cálculo'!C57) -> 0.0965 | F14: =('Memória de Cálculo'!D57) -> 0.0965 | G14: =('Memória de Cálculo'!E57) -> 0.0965 | H14: =('Memória de Cálculo'!F57) -> 0.0965 | I14: =('Memória de Cálculo'!G57) -> 0.0965 | J14: =('Memória de Cálculo'!H57) -> 0.0965 | K14: =('Memória de Cálculo'!I57) -> 0.0965 | ... O14: =('Memória de Cálculo'!M57) -> 0.0965
C15: Total | D15: =SUM(D12:D14) -> 5.0965 | E15: =SUM(E12:E14) -> 5.0965 | F15: =SUM(F12:F14) -> 5.0965 | G15: =SUM(G12:G14) -> 5.0965 | H15: =SUM(H12:H14) -> 5.0965 | I15: =SUM(I12:I14) -> 5.0965 | J15: =SUM(J12:J14) -> 5.0965 | K15: =SUM(K12:K14) -> 5.0965 | ... O15: =SUM(O12:O14) -> 5.0965
C16: Desc. Perdas | D16: =D15*0.97 -> 4.943605 | E16: =E15*0.97 -> 4.943605 | F16: =F15*0.97 -> 4.943605 | G16: =G15*0.97 -> 4.943605 | H16: =H15*0.97 -> 4.943605 | I16: =I15*0.97 -> 4.943605 | J16: =J15*0.97 -> 4.943605 | K16: =K15*0.97 -> 4.943605 | ... O16: =O15*0.97 -> 4.943605
C17: Desc. Auxiliar | D17: =D16*(1-'Energia Aux - Met'!$T$71) -> 4.7002931 | E17: =E16*(1-'Energia Aux - Met'!$T$71) -> 4.7002931 | F17: =F16*(1-'Energia Aux - Met'!$T$71) -> 4.7002931 | G17: =G16*(1-'Energia Aux - Met'!$T$71) -> 4.7002931 | H17: =H16*(1-'Energia Aux - Met'!$T$71) -> 4.7002931 | I17: =I16*(1-'Energia Aux - Met'!$T$71) -> 4.7002931 | J17: =J16*(1-'Energia Aux - Met'!$T$71) -> 4.7002931 | K17: =K16*(1-'Energia Aux - Met'!$T$71) -> 4.7002931 | ... O17: =O16*(1-'Energia Aux - Met'!$T$71) -> 4.7002931
C20: Energia para Venda | D20: JAN | E20: FEV | F20: MAR | G20: ABR | H20: MAI | I20: JUN | J20: JUL | K20: AGO | L20: SET | M20: OUT | N20: NOV | O20: DEZ
B21: Metalurgia | C21: CHESF | D21: ='Memória de Cálculo'!B7 -> 55 | E21: ='Memória de Cálculo'!C7 -> 55 | F21: ='Memória de Cálculo'!D7 -> 55 | G21: ='Memória de Cálculo'!E7 -> 55 | H21: ='Memória de Cálculo'!F7 -> 55 | I21: ='Memória de Cálculo'!G7 -> 55 | J21: ='Memória de Cálculo'!H7 -> 55 | K21: ='Memória de Cálculo'!I7 -> 55 | ... O21: ='Memória de Cálculo'!M7 -> 55
C22: ML | D22: ='Memória de Cálculo'!B8+'Memória de Cálculo'!B9 -> 105 | E22: ='Memória de Cálculo'!C8+'Memória de Cálculo'!C9 -> 105 | F22: ='Memória de Cálculo'!D8+'Memória de Cálculo'!D9 -> 105 | G22: ='Memória de Cálculo'!E8+'Memória de Cálculo'!E9 -> 105 | H22: ='Memória de Cálculo'!F8+'Memória de Cálculo'!F9 -> 105 | I22: ='Memória de Cálculo'!G8+'Memória de Cálculo'!G9 -> 105 | J22: ='Memória de Cálculo'!H8+'Memória de Cálculo'!H9 -> 105 | K22: ='Memória de Cálculo'!I8+'Memória de Cálculo'!I9 -> 105 | ... O22: ='Memória de Cálculo'!M8+'Memória de Cálculo'!M9 -> 105
B23: IPUEIRA | C23: PRIME | D23: ='Memória de Cálculo'!B55 -> 0 | E23: ='Memória de Cálculo'!C55 -> 0 | F23: ='Memória de Cálculo'!D55 -> 0 | G23: ='Memória de Cálculo'!E55 -> 0 | H23: ='Memória de Cálculo'!F55 -> 0 | I23: ='Memória de Cálculo'!G55 -> 0 | J23: ='Memória de Cálculo'!H55 -> 0 | K23: ='Memória de Cálculo'!I55 -> 0 | ... O23: ='Memória de Cálculo'!M55 -> 0
C24: CPFL | D24: ='Memória de Cálculo'!B56 -> 5 | E24: ='Memória de Cálculo'!C56 -> 5 | F24: ='Memória de Cálculo'!D56 -> 5 | G24: ='Memória de Cálculo'!E56 -> 5 | H24: ='Memória de Cálculo'!F56 -> 5 | I24: ='Memória de Cálculo'!G56 -> 5 | J24: ='Memória de Cálculo'!H56 -> 5 | K24: ='Memória de Cálculo'!I56 -> 5 | ... O24: ='Memória de Cálculo'!M56 -> 5
C28: Energia para Consumo | D28: 1T-2025 | E28: 2T-2025 | F28: 3T-2025 | G28: 4T-2025
C29: Metalurgia - CHESF | D29: =AVERAGE(D7:F7) -> 50.724246 | E29: =AVERAGE(G7:I7) -> 50.724246 | F29: =AVERAGE(J7:L7) -> 50.724246 | G29: =AVERAGE(M7:O7) -> 50.724246
C30: Metalurgia - ML | D30: =AVERAGE(D10:F10) -> 132.73032 | E30: =AVERAGE(G10:I10) -> 132.73032 | F30: =AVERAGE(J10:L10) -> 132.73032 | G30: =AVERAGE(M10:O10) -> 132.73032
C31: IPUEIRA | D31: =AVERAGE(D17:F17) -> 4.7002931 | E31: =AVERAGE(G17:I17) -> 4.7002931 | F31: =AVERAGE(J17:L17) -> 4.7002931 | G31: =AVERAGE(M17:O17) -> 4.7002931
C32: Energia para Venda | D32: 1T-2025 | E32: 2T-2025 | F32: 3T-2025 | G32: 4T-2025
C33: Metalurgia | D33: =D5+D8 -> 198.9187 | E33: =E5+E8 -> 198.9187 | F33: =F5+F8 -> 198.9187 | G33: =G5+G8 -> 198.9187
C34: IPUEIRA | D34: =D13 -> 5 | E34: =E13 -> 5 | F34: =F13 -> 5 | G34: =G13 -> 5

Sheet Preços - Mineração Ipueira
B2: Preço para Consumo | C2: 744 | D2: =28*24 -> 672 | E2: 744 | F2: 720 | G2: 744 | H2: 720 | I2: 744 | J2: 744 | K2: 720 | L2: 744 | M2: 720 | N2: 744
B3: Volume de Contratos (MWmédios) | C3: JAN | D3: FEV | E3: MAR | F3: ABR | G3: MAI | H3: JUN | I3: JUL | J3: AGO | K3: SET | L3: OUT | M3: NOV | N3: DEZ
B4: Prime Energy | C4: ='Memória de Cálculo'!B55 -> 0 | D4: ='Memória de Cálculo'!C55 -> 0 | E4: ='Memória de Cálculo'!D55 -> 0 | F4: ='Memória de Cálculo'!E55 -> 0 | G4: ='Memória de Cálculo'!F55 -> 0 | H4: ='Memória de Cálculo'!G55 -> 0 | I4: ='Memória de Cálculo'!H55 -> 0 | J4: ='Memória de Cálculo'!I55 -> 0 | ... N4: ='Memória de Cálculo'!M55 -> 0
B5: CPFL | C5: ='Memória de Cálculo'!B56 -> 5 | D5: ='Memória de Cálculo'!C56 -> 5 | E5: ='Memória de Cálculo'!D56 -> 5 | F5: ='Memória de Cálculo'!E56 -> 5 | G5: ='Memória de Cálculo'!F56 -> 5 | H5: ='Memória de Cálculo'!G56 -> 5 | I5: ='Memória de Cálculo'!H56 -> 5 | J5: ='Memória de Cálculo'!I56 -> 5 | ... N5: ='Memória de Cálculo'!M56 -> 5
B6: Proinfa | C6: ='Memória de Cálculo'!B57 -> 0.0965 | D6: ='Memória de Cálculo'!C57 -> 0.0965 | E6: ='Memória de Cálculo'!D57 -> 0.0965 | F6: ='Memória de Cálculo'!E57 -> 0.0965 | G6: ='Memória de Cálculo'!F57 -> 0.0965 | H6: ='Memória de Cálculo'!G57 -> 0.0965 | I6: ='Memória de Cálculo'!H57 -> 0.0965 | J6: ='Memória de Cálculo'!I57 -> 0.0965 | ... N6: ='Memória de Cálculo'!M57 -> 0.0965
B7: Desc. Perdas | C7: =SUM(C4:C6)*0.97 -> 4.943605 | D7: =SUM(D4:D6)*0.97 -> 4.943605 | E7: =SUM(E4:E6)*0.97 -> 4.943605 | F7: =SUM(F4:F6)*0.97 -> 4.943605 | G7: =SUM(G4:G6)*0.97 -> 4.943605 | H7: =SUM(H4:H6)*0.97 -> 4.943605 | I7: =SUM(I4:I6)*0.97 -> 4.943605 | J7: =SUM(J4:J6)*0.97 -> 4.943605 | ... N7: =SUM(N4:N6)*0.97 -> 4.943605
B8: Desc. Auxiliar
B11: Volume de Contratos (MWh) | C11: JAN | D11: FEV | E11: MAR | F11: ABR | G11: MAI | H11: JUN | I11: JUL | J11: AGO | K11: SET | L11: OUT | M11: NOV | N11: DEZ
B12: Prime Energy | C12: =C4*C2 -> 0 | D12: =D4*D2 -> 0 | E12: =E4*E2 -> 0 | F12: =F4*F2 -> 0 | G12: =G4*G2 -> 0 | H12: =H4*H2 -> 0 | I12: =I4*I2 -> 0 | J12: =J4*J2 -> 0 | ... N12: =N4*N2 -> 0
B13: CPFL | C13: =C5*C2 -> 3720 | D13: =D5*D2 -> 3360 | E13: =E5*E2 -> 3720 | F13: =F5*F2 -> 3600 | G13: =G5*G2 -> 3720 | H13: =H5*H2 -> 3600 | I13: =I5*I2 -> 3720 | J13: =J5*J2 -> 3720 | ... N13: =N5*N2 -> 3720
B14: Proinfa | C14: =C6*C2 -> 71.796 | D14: =D6*D2 -> 64.848 | E14: =E6*E2 -> 71.796 | F14: =F6*F2 -> 69.48 | G14: =G6*G2 -> 71.796 | H14: =H6*H2 -> 69.48 | I14: =I6*I2 -> 71.796 | J14: =J6*J2 -> 71.796 | ... N14: =N6*N2 -> 71.796
C15: =SUM(C13:C14) -> 3791.796 | D15: =SUM(D13:D14) -> 3424.848 | E15: =SUM(E13:E14) -> 3791.796 | F15: =SUM(F13:F14) -> 3669.48 | G15: =SUM(G13:G14) -> 3791.796 | H15: =SUM(H13:H14) -> 3669.48 | I15: =SUM(I13:I14) -> 3791.796 | J15: =SUM(J13:J14) -> 3791.796 | ... N15: =SUM(N13:N14) -> 3791.796
B17: Preços de Consumo (Posto Fábrica) | C17: JAN | D17: FEV | E17: MAR | F17: ABR | G17: MAI | H17: JUN | I17: JUL | J17: AGO | K17: SET | L17: OUT | M17: NOV | N17: DEZ
B18: Média dos Contratos (R$/MWh) | C18: =SUMPRODUCT(C19:C21,C12:C14)/(SUM(C12:C14)*0.97) -> 206.29916 | D18: =SUMPRODUCT(D19:D21,D12:D14)/(SUM(D12:D14)*0.97) -> 206.29916 | E18: =SUMPRODUCT(E19:E21,E12:E14)/(SUM(E12:E14)*0.97) -> 206.29916 | F18: =SUMPRODUCT(F19:F21,F12:F14)/(SUM(F12:F14)*0.97) -> 206.29916 | G18: =SUMPRODUCT(G19:G21,G12:G14)/(SUM(G12:G14)*0.97) -> 206.29916 | H18: =SUMPRODUCT(H19:H21,H12:H14)/(SUM(H12:H14)*0.97) -> 206.29916 | I18: =SUMPRODUCT(I19:I21,I12:I14)/(SUM(I12:I14)*0.97) -> 206.29916 | J18: =SUMPRODUCT(J19:J21,J12:J14)/(SUM(J12:J14)*0.97) -> 206.29916 | ... N18: =SUMPRODUCT(N19:N21,N12:N14)/(SUM(N12:N14)*0.97) -> 206.29916
B19: Prime | C19: 0 | D19: 0 | E19: 0 | F19: 0 | G19: 0 | H19: 0 | I19: 0 | J19: 0 | K19: 0 | L19: 0 | M19: 0 | N19: 0
B20: CPFL | C20: ='Memória de Cálculo'!B67 -> 203.97232 | D20: ='Memória de Cálculo'!C67 -> 203.97232 | E20: ='Memória de Cálculo'!D67 -> 203.97232 | F20: ='Memória de Cálculo'!E67 -> 203.97232 | G20: ='Memória de Cálculo'!F67 -> 203.97232 | H20: ='Memória de Cálculo'!G67 -> 203.97232 | I20: ='Memória de Cálculo'!H67 -> 203.97232 | J20: ='Memória de Cálculo'!I67 -> 203.97232 | ... N20: ='Memória de Cálculo'!M67 -> 203.97232
B21: Proinfa | C21: 0 | D21: 0 | E21: 0 | F21: 0 | G21: 0 | H21: 0 | I21: 0 | J21: 0 | K21: 0 | L21: 0 | M21: 0 | N21: 0
B22: Encargos (R$/MWh)
B23: TUSD Fio | C23: ='Memória de Cálculo'!B71 -> 104.21538 | D23: ='Memória de Cálculo'!C71 -> 115.38131 | E23: ='Memória de Cálculo'!D71 -> 104.21538 | F23: ='Memória de Cálculo'!E71 -> 92.130611 | G23: ='Memória de Cálculo'!F71 -> 89.158656 | H23: ='Memória de Cálculo'!G71 -> 92.130611 | I23: ='Memória de Cálculo'!H71 -> 89.158656 | J23: ='Memória de Cálculo'!I71 -> 89.158656 | ... N23: ='Memória de Cálculo'!M71 -> 89.158656
B24: TUSD Encargos | C24: ='Memória de Cálculo'!B72 -> 50.77 | D24: ='Memória de Cálculo'!C72 -> 50.77 | E24: ='Memória de Cálculo'!D72 -> 50.77 | F24: ='Memória de Cálculo'!E72 -> 54.08 | G24: ='Memória de Cálculo'!F72 -> 54.08 | H24: ='Memória de Cálculo'!G72 -> 54.08 | I24: ='Memória de Cálculo'!H72 -> 54.08 | J24: ='Memória de Cálculo'!I72 -> 54.08 | ... N24: ='Memória de Cálculo'!M72 -> 54.08
B26: Total Encargos Mineração com Desconto %
C29: JAN | D29: FEV | E29: MAR | F29: ABR | G29: MAI | H29: JUN | I29: JUL | J29: AGO | K29: SET | L29: OUT | M29: NOV | N29: DEZ
B30: Preços de Consumo Energia MCP (R$/MWh) | C30: =C18+C23+C24 -> 361.28454 | D30: =D18+D23+D24 -> 372.45047 | E30: =E18+E23+E24 -> 361.28454 | F30: =F18+F23+F24 -> 352.50978 | G30: =G18+G23+G24 -> 349.53782 | H30: =H18+H23+H24 -> 352.50978 | I30: =I18+I23+I24 -> 349.53782 | J30: =J18+J23+J24 -> 349.53782 | ... N30: =N18+N23+N24 -> 349.53782
B32: Preços do Porftólio para Cessão (R$/MWh) | C32: =SUMPRODUCT(C19:C20,C12:C13)/SUM(C12:C13)/0.9075 -> 224.76288 | D32: =SUMPRODUCT(D19:D20,D12:D13)/SUM(D12:D13)/0.9075 -> 224.76288 | E32: =SUMPRODUCT(E19:E20,E12:E13)/SUM(E12:E13)/0.9075 -> 224.76288 | F32: =SUMPRODUCT(F19:F20,F12:F13)/SUM(F12:F13)/0.9075 -> 224.76288 | G32: =SUMPRODUCT(G19:G20,G12:G13)/SUM(G12:G13)/0.9075 -> 224.76288 | H32: =SUMPRODUCT(H19:H20,H12:H13)/SUM(H12:H13)/0.9075 -> 224.76288 | I32: =SUMPRODUCT(I19:I20,I12:I13)/SUM(I12:I13)/0.9075 -> 224.76288 | J32: =SUMPRODUCT(J19:J20,J12:J13)/SUM(J12:J13)/0.9075 -> 224.76288 | ... N32: =SUMPRODUCT(N19:N20,N12:N13)/SUM(N12:N13)/0.9075 -> 224.76288
B34: Preço de Energia no MCP(R$/MWh) | C34: ='Curva de Preços SPOT'!B9 -> 175.43 | D34: ='Curva de Preços SPOT'!C9 -> 175.43 | E34: ='Curva de Preços SPOT'!D9 -> 175.43 | F34: ='Curva de Preços SPOT'!E9 -> 175.43 | G34: ='Curva de Preços SPOT'!F9 -> 175.43 | H34: ='Curva de Preços SPOT'!G9 -> 175.43 | I34: ='Curva de Preços SPOT'!H9 -> 175.43 | J34: ='Curva de Preços SPOT'!I9 -> 175.43 | ... N34: ='Curva de Preços SPOT'!M9 -> 175.43
B37: BASE TRIMESTRAL
C39: 1T-2025 | D39: 2T-2025 | E39: 3T-2025 | F39: 4T-2025
B40: Preços de Consumo Energia MCP (R$/MWh) | C40: =(SUMPRODUCT(C15:E15,C18:E18)+SUMPRODUCT(C23:E23,C15:E15)+SUMPRODUCT(C15:E15,C24:E24))/SUM(C15:E15) -> 364.75839 | D40: =(SUMPRODUCT(F15:H15,F18:H18)+SUMPRODUCT(F23:H23,F15:H15)+SUMPRODUCT(F15:H15,F24:H24))/SUM(F15:H15) -> 351.49735 | E40: =(SUMPRODUCT(I15:K15,I18:K18)+SUMPRODUCT(I23:K23,I15:K15)+SUMPRODUCT(I15:K15,I24:K24))/SUM(I15:K15) -> 350.50694 | F40: =(SUMPRODUCT(L15:N15,L18:N18)+SUMPRODUCT(L23:N23,L15:N15)+SUMPRODUCT(L15:N15,L24:N24))/SUM(L15:N15) -> 350.50694
B42: Preços do Porftólio para Cessão (R$/MWh) | C42: =SUMPRODUCT(C12:E13,C19:E20)/SUM(C12:E13)/0.9075 -> 224.76288 | D42: =SUMPRODUCT(F12:H13,F19:H20)/SUM(F12:H13)/0.9075 -> 224.76288 | E42: =SUMPRODUCT(I12:K13,I19:K20)/SUM(I12:K13)/0.9075 -> 224.76288 | F42: =SUMPRODUCT(L12:N13,L19:N20)/SUM(L12:N13)/0.9075 -> 224.76288
B44: Preço de Energia no MCP(R$/MWh) | C44: =AVERAGE('Curva de Preços SPOT'!B9:D9) -> 175.43 | D44: =AVERAGE('Curva de Preços SPOT'!E9:G9) -> 175.43 | E44: =AVERAGE('Curva de Preços SPOT'!H9:J9) -> 175.43 | F44: =AVERAGE('Curva de Preços SPOT'!K9:M9) -> 175.43

Sheet Preços - Pojuca
B2: Preços Metalurgia
C3: JAN | D3: FEV | E3: MAR | F3: ABR | G3: MAI | H3: JUN | I3: JUL | J3: AGO | K3: SET | L3: OUT | M3: NOV | N3: DEZ
B4: Preços de Consumo Energia CHESF (R$/MWh) | C4: ='Memória de Cálculo'!B22 -> 196.30408 | D4: ='Memória de Cálculo'!C22 -> 196.36728 | E4: ='Memória de Cálculo'!D22 -> 196.17878 | F4: ='Memória de Cálculo'!E22 -> 196.66994 | G4: ='Memória de Cálculo'!F22 -> 197.13329 | H4: ='Memória de Cálculo'!G22 -> 197.59369 | I4: ='Memória de Cálculo'!H22 -> 197.45132 | J4: ='Memória de Cálculo'!I22 -> 198.96971 | ... N4: ='Memória de Cálculo'!M22 -> 198.78871
B6: Preços de Consumo Energia ML (R$/MWh) | C6: ='Memória de Cálculo'!B23 -> 241.06909 | D6: ='Memória de Cálculo'!C23 -> 241.13229 | E6: ='Memória de Cálculo'!D23 -> 240.94378 | F6: ='Memória de Cálculo'!E23 -> 241.43495 | G6: ='Memória de Cálculo'!F23 -> 241.89829 | H6: ='Memória de Cálculo'!G23 -> 242.35869 | I6: ='Memória de Cálculo'!H23 -> 242.21632 | J6: ='Memória de Cálculo'!I23 -> 243.73471 | ... N6: ='Memória de Cálculo'!M23 -> 243.55372
B8: Preços do Porftólio para Cessão CHESF (R$/MWh) | C8: =Preços!$H$5 -> 120.71532 | D8: =Preços!I5 -> 109.54915 | E8: =Preços!J5 -> 0 | F8: =Preços!K5 -> 0 | G8: =Preços!L5 -> 0 | H8: =Preços!M5 -> 0 | I8: =Preços!N5 -> 0 | J8: =Preços!O5 -> 0 | K8: =Preços!P5 -> CHESF | L8: =Preços!$H$5 -> 120.71532 | M8: =Preços!R5 -> 0 | N8: =Preços!S5 -> 0
B10: Preços do Porftólio para Cessão ML (R$/MWh) | C10: ='Memória de Cálculo'!B48 -> 170.86063 | D10: ='Memória de Cálculo'!C48 -> 170.86063 | E10: ='Memória de Cálculo'!D48 -> 170.86063 | F10: ='Memória de Cálculo'!E48 -> 170.86063 | G10: ='Memória de Cálculo'!F48 -> 170.86063 | H10: ='Memória de Cálculo'!G48 -> 170.86063 | I10: ='Memória de Cálculo'!H48 -> 170.86063 | J10: ='Memória de Cálculo'!I48 -> 170.86063 | ... N10: ='Memória de Cálculo'!M48 -> 170.86063
B12: Preço de Energia Uso Energia MCP(R$/MWh) | C12: ='Memória de Cálculo'!B50 -> 232.69378 | D12: ='Memória de Cálculo'!C50 -> 232.74577 | E12: ='Memória de Cálculo'!D50 -> 232.59075 | F12: ='Memória de Cálculo'!E50 -> 232.99499 | G12: ='Memória de Cálculo'!F50 -> 233.37604 | H12: ='Memória de Cálculo'!G50 -> 233.75457 | I12: ='Memória de Cálculo'!H50 -> 233.6369 | J12: ='Memória de Cálculo'!I50 -> 234.88616 | ... N12: ='Memória de Cálculo'!M50 -> 234.73666 | O12: Atualizado com Perdas
B14: Preço de Energia Cessão MCP(R$/MWh) | C14: ='Memória de Cálculo'!B49 -> 175.43 | D14: ='Memória de Cálculo'!C49 -> 175.43 | E14: ='Memória de Cálculo'!D49 -> 175.43 | F14: ='Memória de Cálculo'!E49 -> 175.43 | G14: ='Memória de Cálculo'!F49 -> 175.43 | H14: ='Memória de Cálculo'!G49 -> 175.43 | I14: ='Memória de Cálculo'!H49 -> 175.43 | J14: ='Memória de Cálculo'!I49 -> 175.43 | ... N14: ='Memória de Cálculo'!M49 -> 175.43
B18: Preços Metalurgia
C19: 1T-2025 | D19: 2T-2025 | E19: 3T-2025 | F19: 4T-2025
B20: Preços de Consumo Energia CHESF (R$/MWh) | C20: =SUMPRODUCT('Memória de Cálculo'!$B$22:$D$22,'Memória de Cálculo'!$B$14:$D$14)/SUM('Memória de Cálculo'!$B$14:$D$14) -> 196.28059 | D20: =SUMPRODUCT('Memória de Cálculo'!$E$22:$G$22,'Memória de Cálculo'!$E$14:$G$14)/SUM('Memória de Cálculo'!$E$14:$G$14) -> 197.13232 | E20: =SUMPRODUCT('Memória de Cálculo'!$H$22:$J$22,'Memória de Cálculo'!$H$14:$J$14)/SUM('Memória de Cálculo'!$H$14:$J$14) -> 198.39905 | F20: =SUMPRODUCT('Memória de Cálculo'!$K$22:$M$22,'Memória de Cálculo'!$K$14:$M$14)/SUM('Memória de Cálculo'!$K$14:$M$14) -> 198.78871
B22: Preços de Consumo Energia ML (R$/MWh) | C22: =SUMPRODUCT('Memória de Cálculo'!$B$20:$D$20,'Memória de Cálculo'!$B$23:$D$23)/SUM('Memória de Cálculo'!$B$20:$D$20) -> 241.04559 | D22: =SUMPRODUCT('Memória de Cálculo'!$E$20:$G$20,'Memória de Cálculo'!$E$23:$G$23)/SUM('Memória de Cálculo'!$E$20:$G$20) -> 241.89732 | E22: =SUMPRODUCT('Memória de Cálculo'!$H$20:$J$20,'Memória de Cálculo'!$H$23:$J$23)/SUM('Memória de Cálculo'!$H$20:$J$20) -> 243.16406 | F22: =SUMPRODUCT('Memória de Cálculo'!$K$20:$M$20,'Memória de Cálculo'!$K$23:$M$23)/SUM('Memória de Cálculo'!$K$20:$M$20) -> 243.55372
B24: Preços do Porftólio para Cessão CHESF (R$/MWh) | C24: =Preços!$H$5 -> 120.71532 | D24: =Preços!$H$5 -> 120.71532 | E24: =Preços!$H$5 -> 120.71532 | F24: =Preços!$H$5 -> 120.71532
B26: Preços do Porftólio para Cessão ML (R$/MWh) | C26: =(SUMPRODUCT('Memória de Cálculo'!$B$15:$D$17,'Memória de Cálculo'!$B$24:$D$26)/SUM('Memória de Cálculo'!$B$15:$D$17))/0.9075 -> 170.86063 | D26: =SUMPRODUCT('Memória de Cálculo'!$E$15:$G$17,'Memória de Cálculo'!$E$24:$G$26)/SUM('Memória de Cálculo'!$E$15:$G$17)/0.9075 -> 170.86063 | E26: =SUMPRODUCT('Memória de Cálculo'!$H$15:$J$17,'Memória de Cálculo'!$H$24:$J$26)/SUM('Memória de Cálculo'!$H$15:$J$17)/0.9075 -> 170.86063 | F26: =SUMPRODUCT('Memória de Cálculo'!$K$15:$M$17,'Memória de Cálculo'!$K$24:$M$26)/SUM('Memória de Cálculo'!$K$15:$M$17)/0.9075 -> 170.86063
B28: Preço de Energia Uso Energia MCP(R$/MWh) | C28: =AVERAGE('Memória de Cálculo'!$B$50:$D$50) -> 232.67676 | D28: =AVERAGE('Memória de Cálculo'!$E$50:$G$50) -> 233.3752 | E28: =AVERAGE('Memória de Cálculo'!$H$50:$J$50) -> 234.41991 | F28: =AVERAGE('Memória de Cálculo'!$K$50:$M$50) -> 234.73666
B30: Preço de Energia Cessão MCP(R$/MWh) | C30: =AVERAGE('Memória de Cálculo'!$B$76:$D$76) -> 175.43 | D30: =AVERAGE('Memória de Cálculo'!$E$76:$G$76) -> 175.43 | E30: =AVERAGE('Memória de Cálculo'!$H$76:$J$76) -> 175.43 | F30: =AVERAGE('Memória de Cálculo'!$K$76:$M$76) -> 175.43

Sheet Curva de Preços SPOT
A2: Curva BBCE Incentivada 50% - 01/07/2024
A3: Mês | B3: 45658 | C3: 45689 | D3: 45717 | E3: 45748 | F3: 45778 | G3: 45809 | H3: 45839 | I3: 45870 | J3: 45901 | K3: 45931 | L3: 45962 | M3: 45992
A4: Valor | B4: 211.13 | C4: 211.13 | D4: 211.13 | E4: 211.13 | F4: 211.13 | G4: 211.13 | H4: 211.13 | I4: 211.13 | J4: 211.13 | K4: 211.13 | L4: 211.13 | M4: 211.13
A7: Curva BBCE Convencional - 01/07/2024
A8: Mês | B8: 45658 | C8: 45689 | D8: 45717 | E8: 45748 | F8: 45778 | G8: 45809 | H8: 45839 | I8: 45870 | J8: 45901 | K8: 45931 | L8: 45962 | M8: 45992
A9: Valor | B9: 175.43 | C9: 175.43 | D9: 175.43 | E9: 175.43 | F9: 175.43 | G9: 175.43 | H9: 175.43 | I9: 175.43 | J9: 175.43 | K9: 175.43 | L9: 175.43 | M9: 175.43

Sheet Energia Aux - Met
B3: Mês | C3: Energia Fornos Fora Ponta (717007) | D3: Energia Fornos Hora Ponta (717008) | E3: Subtotal FORNOS | G3: Sinterização + Aux Fornos FP (Direto) | H3: Sinterização + Aux Fornos HP (Direto) | I3: Subtotal | K3: Auxiliar Fora Ponta (Sem Sinterização e Forno) (717003) | L3: Auxiliar Hora Ponta (Sem Sinterização e Forno) (717004) | M3: Subtotal Aux | O3: Medidor SMART1 FP | P3: Medidor SMART1 HP | Q3: TOTAL Medidor SMART1 | S3: Forno | T3: Auxiliar | V3: 717007 | W3: 717008 | X3: 717003 | Y3: 717004
B4: 43466 | C4: ='[1]Consumo Diário'!$C$42 -> 128045.3 | D4: ='[1]Consumo Diário'!$D$42 -> 1038.452 | E4: =C4+D4 -> 129083.75 | G4: =O4-C4-K4 -> 4251.2206 | H4: =P4-D4-L4 -> 338.97115 | I4: =G4+H4 -> 4590.1917 | K4: ='[1]Consumo Diário'!$DX$42 -> 6649.0374 | L4: ='[1]Consumo Diário'!$DY$42 -> 163.88885 | M4: =K4+L4 -> 6812.9263 | O4: ='[1]Consumo Diário'!$DS$42 -> 138945.56 | P4: ='[1]Consumo Diário'!$DT$42 -> 1541.312 | Q4: =O4+P4 -> 140486.87 | S4: =(E4+I4)/Q4 -> 0.95150489 | T4: =M4/Q4 -> 0.048495111 | V4: =(C4+G4)/Q4 -> 0.94170025 | W4: =(D4+H4)/Q4 -> 0.0098046399 | X4: =K4/Q4 -> 0.047328533 | Y4: =L4/Q4 -> 0.0011665777
B5: 43497 | C5: ='[2]Consumo Diário'!$C$42 -> 117316.54 | D5: ='[2]Consumo Diário'!$D$42 -> 1002.269 | E5: =C5+D5 -> 118318.81 | G5: =O5-C5-K5 -> 4164.4959 | H5: =P5-D5-L5 -> 240.19137 | I5: =G5+H5 -> 4404.6873 | K5: ='[2]Consumo Diário'!$DX$42 -> 5975.6211 | L5: ='[2]Consumo Diário'!$DY$42 -> 211.75563 | M5: =K5+L5 -> 6187.3767 | O5: ='[2]Consumo Diário'!$DS$42 -> 127456.66 | P5: ='[2]Consumo Diário'!$DT$42 -> 1454.216 | Q5: =O5+P5 -> 128910.87 | S5: =(E5+I5)/Q5 -> 0.95200268 | T5: =M5/Q5 -> 0.047997322 | V5: =(C5+G5)/Q5 -> 0.94236454 | W5: =(D5+H5)/Q5 -> 0.0096381347 | X5: =K5/Q5 -> 0.04635467 | Y5: =L5/Q5 -> 0.0016426514
B6: 43525 | C6: ='[3]Consumo Diário'!$C$42 -> 130503.71 | D6: ='[3]Consumo Diário'!$D$42 -> 955.99 | E6: =C6+D6 -> 131459.7 | G6: =O6-C6-K6 -> 4776.9969 | H6: =P6-D6-L6 -> 204.1474 | I6: =G6+H6 -> 4981.1443 | K6: ='[3]Consumo Diário'!$DX$42 -> 6735.3501 | L6: ='[3]Consumo Diário'!$DY$42 -> 269.4556 | M6: =K6+L6 -> 7004.8057 | O6: ='[3]Consumo Diário'!$DS$42 -> 142016.06 | P6: ='[3]Consumo Diário'!$DT$42 -> 1429.593 | Q6: =O6+P6 -> 143445.65 | S6: =(E6+I6)/Q6 -> 0.95116753 | T6: =M6/Q6 -> 0.048832472 | V6: =(C6+G6)/Q6 -> 0.94307988 | W6: =(D6+H6)/Q6 -> 0.0080876443 | X6: =K6/Q6 -> 0.046954021 | Y6: =L6/Q6 -> 0.0018784508
B7: 43556 | C7: ='[4]Consumo Diário'!$C$42 -> 126449.83 | D7: ='[4]Consumo Diário'!$D$42 -> 1016.962 | E7: =C7+D7 -> 127466.79 | G7: =O7-C7-K7 -> 5057.7774 | H7: =P7-D7-L7 -> 254.58675 | I7: =G7+H7 -> 5312.3642 | K7: ='[4]Consumo Diário'!$DX$42 -> 6441.9156 | L7: ='[4]Consumo Diário'!$DY$42 -> 265.04825 | M7: =K7+L7 -> 6706.9638 | O7: ='[4]Consumo Diário'!$DS$42 -> 137949.52 | P7: ='[4]Consumo Diário'!$DT$42 -> 1536.597 | Q7: =O7+P7 -> 139486.12 | S7: =(E7+I7)/Q7 -> 0.95191662 | T7: =M7/Q7 -> 0.048083379 | V7: =(C7+G7)/Q7 -> 0.94280067 | W7: =(D7+H7)/Q7 -> 0.009115952 | X7: =K7/Q7 -> 0.046183202 | Y7: =L7/Q7 -> 0.0019001765
B8: 43586 | C8: ='[5]Consumo Diário'!$C$42 -> 128349.51 | D8: ='[5]Consumo Diário'!$D$42 -> 1006.995 | E8: =C8+D8 -> 129356.5 | G8: =O8-C8-K8 -> 5059.0495 | H8: =P8-D8-L8 -> 241.33126 | I8: =G8+H8 -> 5300.3808 | K8: ='[5]Consumo Diário'!$DX$42 -> 5845.8615 | L8: ='[5]Consumo Diário'!$DY$42 -> 249.47074 | M8: =K8+L8 -> 6095.3322 | O8: ='[5]Consumo Diário'!$DS$42 -> 139254.42 | P8: ='[5]Consumo Diário'!$DT$42 -> 1497.797 | Q8: =O8+P8 -> 140752.21 | S8: =(E8+I8)/Q8 -> 0.95669459 | T8: =M8/Q8 -> 0.043305409 | V8: =(C8+G8)/Q8 -> 0.94782563 | W8: =(D8+H8)/Q8 -> 0.0088689637 | X8: =K8/Q8 -> 0.041532999 | Y8: =L8/Q8 -> 0.0017724108
B9: 43617 | C9: ='[6]Consumo Diário'!$C$42 -> 102197.69 | D9: ='[6]Consumo Diário'!$D$42 -> 902.189 | E9: =C9+D9 -> 103099.88 | G9: =O9-C9-K9 -> 4162.7027 | H9: =P9-D9-L9 -> 238.21771 | I9: =G9+H9 -> 4400.9204 | K9: ='[6]Consumo Diário'!$DX$42 -> 6155.3413 | L9: ='[6]Consumo Diário'!$DY$42 -> 241.31429 | M9: =K9+L9 -> 6396.6556 | O9: ='[6]Consumo Diário'!$DS$42 -> 112515.73 | P9: ='[6]Consumo Diário'!$DT$42 -> 1381.721 | Q9: =O9+P9 -> 113897.46 | S9: =(E9+I9)/Q9 -> 0.94383847 | T9: =M9/Q9 -> 0.056161532 | V9: =(C9+G9)/Q9 -> 0.93382589 | W9: =(D9+H9)/Q9 -> 0.010012574 | X9: =K9/Q9 -> 0.054042834 | Y9: =L9/Q9 -> 0.0021186978
B10: 43647 | C10: ='[7]Consumo Diário'!$C$42 -> 91509.02 | D10: ='[7]Consumo Diário'!$D$42 -> 1139.96 | E10: =C10+D10 -> 92648.98 | G10: =O10-C10-K10 -> 4034.2526 | H10: =P10-D10-L10 -> 294.59516 | I10: =G10+H10 -> 4328.8477 | K10: ='[7]Consumo Diário'!$DX$42 -> 5707.7444 | L10: ='[7]Consumo Diário'!$DY$42 -> 281.91484 | M10: =K10+L10 -> 5989.6593 | O10: ='[7]Consumo Diário'!$DS$42 -> 101251.02 | P10: ='[7]Consumo Diário'!$DT$42 -> 1716.47 | Q10: =O10+P10 -> 102967.49 | S10: =(E10+I10)/Q10 -> 0.94182961 | T10: =M10/Q10 -> 0.058170394 | V10: =(C10+G10)/Q10 -> 0.92789749 | W10: =(D10+H10)/Q10 -> 0.013932118 | X10: =K10/Q10 -> 0.055432492 | Y10: =L10/Q10 -> 0.0027379015
B11: 43678 | C11: ='[8]Consumo Diário'!$C$42 -> 91402.032 | D11: ='[8]Consumo Diário'!$D$42 -> 1125.498 | E11: =C11+D11 -> 92527.53 | G11: =O11-C11-K11 -> 3977.6534 | H11: =P11-D11-L11 -> 263.3656 | I11: =G11+H11 -> 4241.019 | K11: ='[8]Consumo Diário'!$DX$42 -> 5616.7726 | L11: ='[8]Consumo Diário'!$DY$42 -> 267.5464 | M11: =K11+L11 -> 5884.319 | O11: ='[8]Consumo Diário'!$DS$42 -> 100996.46 | P11: ='[8]Consumo Diário'!$DT$42 -> 1656.41 | Q11: =O11+P11 -> 102652.87 | S11: =(E11+I11)/Q11 -> 0.9426775 | T11: =M11/Q11 -> 0.0573225 | V11: =(C11+G11)/Q11 -> 0.92914779 | W11: =(D11+H11)/Q11 -> 0.013529711 | X11: =K11/Q11 -> 0.054716178 | Y11: =L11/Q11 -> 0.0026063217
B12: 43709 | C12: ='[9]Consumo Diário'!$C$42 -> 88616.604 | D12: ='[9]Consumo Diário'!$D$42 -> 1006.646 | E12: =C12+D12 -> 89623.25 | G12: =O12-C12-K12 -> 3964.7494 | H12: =P12-D12-L12 -> 260.5902 | I12: =G12+H12 -> 4225.3396 | K12: ='[9]Consumo Diário'!$DX$42 -> 5364.5346 | L12: ='[9]Consumo Diário'!$DY$42 -> 238.1908 | M12: =K12+L12 -> 5602.7254 | O12: ='[9]Consumo Diário'!$DS$42 -> 97945.888 | P12: ='[9]Consumo Diário'!$DT$42 -> 1505.427 | Q12: =O12+P12 -> 99451.315 | S12: =(E12+I12)/Q12 -> 0.94366364 | T12: =M12/Q12 -> 0.056336363 | V12: =(C12+G12)/Q12 -> 0.93092136 | W12: =(D12+H12)/Q12 -> 0.012742277 | X12: =K12/Q12 -> 0.053941314 | Y12: =L12/Q12 -> 0.0023950493
B13: 43739 | C13: ='[10]Consumo Diário'!$C$42 -> 92023.942 | D13: ='[10]Consumo Diário'!$D$42 -> 1226.168 | E13: =C13+D13 -> 93250.11 | G13: =O13-C13-K13 -> 3226.0329 | H13: =P13-D13-L13 -> 199.449 | I13: =G13+H13 -> 3425.4819 | K13: ='[10]Consumo Diário'!$DT$42 -> 5718.3921 | L13: ='[10]Consumo Diário'!$DU$42 -> 287.734 | M13: =K13+L13 -> 6006.1261 | O13: ='[10]Consumo Diário'!$DO$42 -> 100968.37 | P13: ='[10]Consumo Diário'!$DP$42 -> 1713.351 | Q13: =O13+P13 -> 102681.72 | S13: =(E13+I13)/Q13 -> 0.94150735 | T13: =M13/Q13 -> 0.058492653 | V13: =(C13+G13)/Q13 -> 0.9276235 | W13: =(D13+H13)/Q13 -> 0.013883844 | X13: =K13/Q13 -> 0.05569046 | Y13: =L13/Q13 -> 0.0028021931
B14: 43770 | C14: ='[11]Consumo Diário'!$C$42 -> 94358.725 | D14: ='[11]Consumo Diário'!$D$42 -> 1006.117 | E14: =C14+D14 -> 95364.842 | G14: =O14-C14-K14 -> 3695.702 | H14: =P14-D14-L14 -> 204.4586 | I14: =G14+H14 -> 3900.1606 | K14: ='[11]Consumo Diário'!$DT$42 -> 5397.622 | L14: ='[11]Consumo Diário'!$DU$42 -> 243.5204 | M14: =K14+L14 -> 5641.1424 | O14: ='[11]Consumo Diário'!$DO$42 -> 103452.05 | P14: ='[11]Consumo Diário'!$DP$42 -> 1454.096 | Q14: =O14+P14 -> 104906.15 | S14: =(E14+I14)/Q14 -> 0.94622677 | T14: =M14/Q14 -> 0.053773231 | V14: =(C14+G14)/Q14 -> 0.93468716 | W14: =(D14+H14)/Q14 -> 0.011539606 | X14: =K14/Q14 -> 0.051451914 | Y14: =L14/Q14 -> 0.0023213168
B15: 43800 | C15: ='[12]Consumo Diário'!$C$42 -> 125856.38 | D15: ='[12]Consumo Diário'!$D$42 -> 948.05 | E15: =C15+D15 -> 126804.43 | G15: =O15-C15-K15 -> 4804.4613 | H15: =P15-D15-L15 -> 306.7694 | I15: =G15+H15 -> 5111.2307 | K15: ='[12]Consumo Diário'!$DT$42 -> 6743.4747 | L15: ='[12]Consumo Diário'!$DU$42 -> 295.4246 | M15: =K15+L15 -> 7038.8993 | O15: ='[12]Consumo Diário'!$DO$42 -> 137404.32 | P15: ='[12]Consumo Diário'!$DP$42 -> 1550.244 | Q15: =O15+P15 -> 138954.56 | S15: =(E15+I15)/Q15 -> 0.94934388 | T15: =M15/Q15 -> 0.050656123 | V15: =(C15+G15)/Q15 -> 0.94031345 | W15: =(D15+H15)/Q15 -> 0.0090304299 | X15: =K15/Q15 -> 0.048530072 | Y15: =L15/Q15 -> 0.0021260519
B16: 43831 | C16: ='[13]Consumo Diário'!$C$42 -> 126534.03 | D16: ='[13]Consumo Diário'!$D$42 -> 1003.668 | E16: =C16+D16 -> 127537.69 | G16: =O16-C16-K16 -> 4892.1756 | H16: =P16-D16-L16 -> 294.8714 | I16: =G16+H16 -> 5187.047 | K16: ='[13]Consumo Diário'!$DT$42 -> 6989.1944 | L16: ='[13]Consumo Diário'!$DU$42 -> 293.5456 | M16: =K16+L16 -> 7282.74 | O16: ='[13]Consumo Diário'!$DO$42 -> 138415.4 | P16: ='[13]Consumo Diário'!$DP$42 -> 1592.085 | Q16: =O16+P16 -> 140007.48 | S16: =(E16+I16)/Q16 -> 0.94798321 | T16: =M16/Q16 -> 0.052016792 | V16: =(C16+G16)/Q16 -> 0.93870842 | W16: =(D16+H16)/Q16 -> 0.0092747858 | X16: =K16/Q16 -> 0.04992015 | Y16: =L16/Q16 -> 0.0020966423
B17: 43862 | C17: ='[13]Consumo Diário'!$C$42 -> 126534.03 | D17: ='[13]Consumo Diário'!$D$42 -> 1003.668 | E17: =C17+D17 -> 127537.69 | G17: =O17-C17-K17 -> 1747.0056 | H17: =P17-D17-L17 -> 103.4764 | I17: =G17+H17 -> 1850.482 | K17: ='[13]Consumo Diário'!$DT$42 -> 6989.1944 | L17: ='[13]Consumo Diário'!$DU$42 -> 293.5456 | M17: =K17+L17 -> 7282.74 | O17: ='[14]Consumo Diário'!$DN$42 -> 135270.23 | P17: ='[14]Consumo Diário'!$DO$42 -> 1400.69 | Q17: =O17+P17 -> 136670.92 | S17: =(E17+I17)/Q17 -> 0.94671332 | T17: =M17/Q17 -> 0.053286685 | V17: =(C17+G17)/Q17 -> 0.93861251 | W17: =(D17+H17)/Q17 -> 0.0081008047 | X17: =K17/Q17 -> 0.051138857 | Y17: =L17/Q17 -> 0.0021478279
B18: 43891 | C18: ='[14]Consumo Diário'!$C$42 -> 124104.38 | D18: ='[14]Consumo Diário'!$D$42 -> 891.38 | E18: =C18+D18 -> 124995.76 | G18: =O18-C18-K18 -> 10504.428 | H18: =P18-D18-L18 -> 465.1356 | I18: =G18+H18 -> 10969.563 | K18: ='[14]Consumo Diário'!$DS$42 -> 6540.3074 | L18: ='[14]Consumo Diário'!$DT$42 -> 261.8614 | M18: =K18+L18 -> 6802.1688 | O18: ='[15]Consumo Diário'!$ED$42 -> 141149.12 | P18: ='[15]Consumo Diário'!$EE$42 -> 1618.377 | Q18: =O18+P18 -> 142767.5 | S18: =(E18+I18)/Q18 -> 0.95235492 | T18: =M18/Q18 -> 0.04764508 | V18: =(C18+G18)/Q18 -> 0.94285335 | W18: =(D18+H18)/Q18 -> 0.0095015717 | X18: =K18/Q18 -> 0.045810899 | Y18: =L18/Q18 -> 0.0018341808
B19: 43922 | C19: ='[15]Consumo Diário'!$C$42 -> 129409.29 | D19: ='[15]Consumo Diário'!$D$42 -> 1008.75 | E19: =C19+D19 -> 130418.04 | G19: =O19-C19-K19 -> 7294.4596 | H19: =P19-D19-L19 -> 303.34354 | I19: =G19+H19 -> 7597.8031 | K19: ='[15]Consumo Diário'!$EI$42 -> 6895.1214 | L19: ='[15]Consumo Diário'!$EJ$42 -> 306.28346 | M19: =K19+L19 -> 7201.4049 | O19: ='[16]Consumo Diário'!$ED$42 -> 143598.87 | P19: ='[15]Consumo Diário'!$EE$42 -> 1618.377 | Q19: =O19+P19 -> 145217.25 | S19: =(E19+I19)/Q19 -> 0.95040944 | T19: =M19/Q19 -> 0.049590563 | V19: =(C19+G19)/Q19 -> 0.94137405 | W19: =(D19+H19)/Q19 -> 0.0090353838 | X19: =K19/Q19 -> 0.047481423 | Y19: =L19/Q19 -> 0.0021091397
B20: 43952 | C20: ='[17]Consumo Diário'!$C$42 -> 137360.64 | D20: ='[17]Consumo Diário'!$D$42 -> 950.994 | E20: =C20+D20 -> 138311.64 | G20: =O20-C20-K20 -> 4897.5224 | H20: =P20-D20-L20 -> 261.48373 | I20: =G20+H20 -> 5159.0062 | K20: ='[17]Consumo Diário'!$EI$42 -> 6856.1426 | L20: ='[17]Consumo Diário'!$EJ$42 -> 290.46927 | M20: =K20+L20 -> 7146.6118 | O20: ='[17]Consumo Diário'!$ED$42 -> 149114.31 | P20: ='[17]Consumo Diário'!$EE$42 -> 1502.947 | Q20: =O20+P20 -> 150617.26 | S20: =(E20+I20)/Q20 -> 0.95255117 | T20: =M20/Q20 -> 0.047448825 | V20: =(C20+G20)/Q20 -> 0.94450112 | W20: =(D20+H20)/Q20 -> 0.0080500586 | X20: =K20/Q20 -> 0.0455203 | Y20: =L20/Q20 -> 0.0019285258
B21: 43983 | C21: ='[18]Consumo Diário'!$C$42 -> 132342.08 | D21: ='[18]Consumo Diário'!$D$42 -> 961.615 | E21: =C21+D21 -> 133303.69 | G21: =O21-C21-K21 -> 4988.1318 | H21: =P21-D21-L21 -> 309.07096 | I21: =G21+H21 -> 5297.2027 | K21: ='[18]Consumo Diário'!$EI$42 -> 6473.5532 | L21: ='[18]Consumo Diário'!$EJ$42 -> 297.53504 | M21: =K21+L21 -> 6771.0883 | O21: ='[18]Consumo Diário'!$ED$42 -> 143803.76 | P21: ='[18]Consumo Diário'!$EE$42 -> 1568.221 | Q21: =O21+P21 -> 145371.99 | S21: =(E21+I21)/Q21 -> 0.95342233 | T21: =M21/Q21 -> 0.046577669 | V21: =(C21+G21)/Q21 -> 0.9446814 | W21: =(D21+H21)/Q21 -> 0.0087409274 | X21: =K21/Q21 -> 0.044530954 | Y21: =L21/Q21 -> 0.0020467151
B22: 44013 | C22: ='[19]Consumo Diário'!$C$42 -> 136582.73 | D22: ='[19]Consumo Diário'!$D$42 -> 1046.4179 | E22: =C22+D22 -> 137629.15 | G22: =O22-C22-K22 -> 4923.4702 | H22: =P22-D22-L22 -> 315.10317 | I22: =G22+H22 -> 5238.5733 | K22: ='[19]Consumo Diário'!$EI$42 -> 6750.2004 | L22: ='[19]Consumo Diário'!$EJ$42 -> 350.86093 | M22: =K22+L22 -> 7101.0614 | O22: ='[19]Consumo Diário'!$ED$42 -> 148256.4 | P22: ='[19]Consumo Diário'!$EE$42 -> 1712.382 | Q22: =O22+P22 -> 149968.78 | S22: =(E22+I22)/Q22 -> 0.95264974 | T22: =M22/Q22 -> 0.047350264 | V22: =(C22+G22)/Q22 -> 0.94357104 | W22: =(D22+H22)/Q22 -> 0.0090786967 | X22: =K22/Q22 -> 0.045010704 | Y22: =L22/Q22 -> 0.0023395598
B23: 44044 | C23: ='[20]Consumo Diário'!$C$42 -> 139258.68 | D23: ='[20]Consumo Diário'!$D$42 -> 1017.025 | E23: =C23+D23 -> 140275.7 | G23: =O23-C23-K23 -> 4943.6309 | H23: =P23-D23-L23 -> 284.3839 | I23: =G23+H23 -> 5228.0148 | K23: ='[20]Consumo Diário'!$EI$42 -> 7040.4301 | L23: ='[20]Consumo Diário'!$EJ$42 -> 281.9441 | M23: =K23+L23 -> 7322.3742 | O23: ='[20]Consumo Diário'!$ED$42 -> 151242.74 | P23: ='[20]Consumo Diário'!$EE$42 -> 1583.353 | Q23: =O23+P23 -> 152826.09 | S23: =(E23+I23)/Q23 -> 0.95208689 | T23: =M23/Q23 -> 0.047913115 | V23: =(C23+G23)/Q23 -> 0.94357127 | W23: =(D23+H23)/Q23 -> 0.0085156197 | X23: =K23/Q23 -> 0.046068246 | Y23: =L23/Q23 -> 0.0018448688
B24: 44075 | C24: 130047.23 | D24: 1037.209 | E24: =C24+D24 -> 131084.44 | G24: =O24-C24-K24 -> 4692.3854 | H24: =P24-D24-L24 -> 285.72194 | I24: =G24+H24 -> 4978.1073 | K24: 6644.4096 | L24: 266.65506 | M24: =K24+L24 -> 6911.0647 | O24: 141384.02 | P24: 1589.586 | Q24: =O24+P24 -> 142973.61 | S24: =(E24+I24)/Q24 -> 0.95166196 | T24: =M24/Q24 -> 0.048338045 | V24: =(C24+G24)/Q24 -> 0.94240898 | W24: =(D24+H24)/Q24 -> 0.009252973 | X24: =K24/Q24 -> 0.04647298 | Y24: =L24/Q24 -> 0.0018650649
B25: 44105 | C25: 131971.47 | D25: 959.069 | E25: =C25+D25 -> 132930.53 | G25: =O25-C25-K25 -> 5206.2974 | H25: =P25-D25-L25 -> 280.57778 | I25: =G25+H25 -> 5486.8751 | K25: 6886.7356 | L25: 308.77722 | M25: =K25+L25 -> 7195.5129 | O25: 144064.5 | P25: 1548.424 | Q25: =O25+P25 -> 145612.92 | S25: =(E25+I25)/Q25 -> 0.95058465 | T25: =M25/Q25 -> 0.049415346 | V25: =(C25+G25)/Q25 -> 0.94207135 | W25: =(D25+H25)/Q25 -> 0.008513302 | X25: =K25/Q25 -> 0.047294811 | Y25: =L25/Q25 -> 0.0021205345
B26: 44136 | C26: 105349.79 | D26: 903.231 | E26: =C26+D26 -> 106253.02 | G26: =O26-C26-K26 -> 3976.5511 | H26: =P26-D26-L26 -> 280.28073 | I26: =G26+H26 -> 4256.8318 | K26: 5328.8666 | L26: 259.90827 | M26: =K26+L26 -> 5588.7749 | O26: 114655.2 | P26: 1443.42 | Q26: =O26+P26 -> 116098.62 | S26: =(E26+I26)/Q26 -> 0.95186183 | T26: =M26/Q26 -> 0.048138167 | V26: =(C26+G26)/Q26 -> 0.94166781 | W26: =(D26+H26)/Q26 -> 0.01019402 | X26: =K26/Q26 -> 0.045899482 | Y26: =L26/Q26 -> 0.0022386852
B27: 44166 | C27: 134346.26 | D27: 1021.576 | E27: =C27+D27 -> 135367.83 | G27: =O27-C27-K27 -> 4945.3745 | H27: =P27-D27-L27 -> 273.81942 | I27: =G27+H27 -> 5219.1939 | K27: 6782.3414 | L27: 295.96458 | M27: =K27+L27 -> 7078.306 | O27: 146073.97 | P27: 1591.36 | Q27: =O27+P27 -> 147665.33 | S27: =(E27+I27)/Q27 -> 0.95206522 | T27: =M27/Q27 -> 0.047934785 | V27: =(C27+G27)/Q27 -> 0.94329271 | W27: =(D27+H27)/Q27 -> 0.0087725087 | X27: =K27/Q27 -> 0.045930492 | Y27: =L27/Q27 -> 0.0020042929
B28: 44197 | C28: 136708.42 | D28: 933.0493 | E28: =C28+D28 -> 137641.46 | G28: =O28-C28-K28 -> 4967.805 | H28: =P28-D28-L28 -> 252.57243 | I28: =G28+H28 -> 5220.3775 | K28: 6982.6417 | L28: 300.43627 | M28: =K28+L28 -> 7283.0779 | O28: 148658.86 | P28: 1486.058 | Q28: =O28+P28 -> 150144.92 | S28: =(E28+I28)/Q28 -> 0.95149301 | T28: =M28/Q28 -> 0.048506989 | V28: =(C28+G28)/Q28 -> 0.9435965 | W28: =(D28+H28)/Q28 -> 0.0078965158 | X28: =K28/Q28 -> 0.046506013 | Y28: =L28/Q28 -> 0.0020009753
B29: 44228 | C29: 121541.18 | D29: 849.9355 | E29: =C29+D29 -> 122391.12 | G29: =O29-C29-K29 -> 4592.6935 | H29: =P29-D29-L29 -> 255.72467 | I29: =G29+H29 -> 4848.4182 | K29: 6289.7639 | L29: 287.29583 | M29: =K29+L29 -> 6577.0597 | O29: 132423.64 | P29: 1392.956 | Q29: =O29+P29 -> 133816.59 | S29: =(E29+I29)/Q29 -> 0.95085019 | T29: =M29/Q29 -> 0.049149807 | V29: =(C29+G29)/Q29 -> 0.94258769 | W29: =(D29+H29)/Q29 -> 0.0082625042 | X29: =K29/Q29 -> 0.047002869 | Y29: =L29/Q29 -> 0.0021469372
B30: 44256 | C30: 139845.57 | D30: 977.9499 | E30: =C30+D30 -> 140823.52 | G30: =O30-C30-K30 -> 5056.7823 | H30: =P30-D30-L30 -> 308.69939 | I30: =G30+H30 -> 5365.4817 | K30: 6941.3565 | L30: 339.79071 | M30: =K30+L30 -> 7281.1472 | O30: 151843.71 | P30: 1626.44 | Q30: =O30+P30 -> 153470.15 | S30: =(E30+I30)/Q30 -> 0.95255659 | T30: =M30/Q30 -> 0.04744341 | V30: =(C30+G30)/Q30 -> 0.94417288 | W30: =(D30+H30)/Q30 -> 0.0083837104 | X30: =K30/Q30 -> 0.045229359 | Y30: =L30/Q30 -> 0.0022140509
B31: 44287 | C31: 133727.98 | D31: 844.8968 | E31: =C31+D31 -> 134572.87 | G31: =O31-C31-K31 -> 4793.3791 | H31: =P31-D31-L31 -> 262.06845 | I31: =G31+H31 -> 5055.4476 | K31: 6537.5212 | L31: 285.99275 | M31: =K31+L31 -> 6823.5139 | O31: 145058.88 | P31: 1392.958 | Q31: =O31+P31 -> 146451.84 | S31: =(E31+I31)/Q31 -> 0.9534078 | T31: =M31/Q31 -> 0.046592205 | V31: =(C31+G31)/Q31 -> 0.94584923 | W31: =(D31+H31)/Q31 -> 0.0075585618 | X31: =K31/Q31 -> 0.044639394 | Y31: =L31/Q31 -> 0.001952811
B32: 44317 | C32: 140733.49 | D32: 955.1982 | E32: =C32+D32 -> 141688.69 | G32: =O32-C32-K32 -> 4828.9359 | H32: =P32-D32-L32 -> 274.88061 | I32: =G32+H32 -> 5103.8165 | K32: 6828.5203 | L32: 322.96019 | M32: =K32+L32 -> 7151.4805 | O32: 152390.95 | P32: 1553.039 | Q32: =O32+P32 -> 153943.99 | S32: =(E32+I32)/Q32 -> 0.95354492 | T32: =M32/Q32 -> 0.046455081 | V32: =(C32+G32)/Q32 -> 0.94555449 | W32: =(D32+H32)/Q32 -> 0.0079904309 | X32: =K32/Q32 -> 0.044357173 | Y32: =L32/Q32 -> 0.0020979071
B33: 44348 | C33: 121078.1 | D33: 948.3736 | E33: =C33+D33 -> 122026.47 | G33: =O33-C33-K33 -> 4382.9937 | H33: =P33-D33-L33 -> 283.04309 | I33: =G33+H33 -> 4666.0368 | K33: 6240.7079 | L33: 323.10431 | M33: =K33+L33 -> 6563.8122 | O33: 131701.8 | P33: 1554.521 | Q33: =O33+P33 -> 133256.32 | S33: =(E33+I33)/Q33 -> 0.95074296 | T33: =M33/Q33 -> 0.049257041 | V33: =(C33+G33)/Q33 -> 0.941502 | W33: =(D33+H33)/Q33 -> 0.0092409625 | X33: =K33/Q33 -> 0.046832359 | Y33: =L33/Q33 -> 0.0024246828
B34: 44378 | C34: 139929.78 | D34: 968.3854 | E34: =C34+D34 -> 140898.17 | G34: =O34-C34-K34 -> 5005.9059 | H34: =P34-D34-L34 -> 303.02506 | I34: =G34+H34 -> 5308.931 | K34: 6769.8177 | L34: 354.57654 | M34: =K34+L34 -> 7124.3942 | O34: 151705.51 | P34: 1625.987 | Q34: =O34+P34 -> 153331.49 | S34: =(E34+I34)/Q34 -> 0.953536 | T34: =M34/Q34 -> 0.046463999 | V34: =(C34+G34)/Q34 -> 0.94524409 | W34: =(D34+H34)/Q34 -> 0.0082919069 | X34: =K34/Q34 -> 0.044151515 | Y34: =L34/Q34 -> 0.0023124835
B35: 44409 | C35: 142073.76 | D35: 979.4797 | E35: =C35+D35 -> 143053.24 | G35: =O35-C35-K35 -> 5281.6308 | H35: =P35-D35-L35 -> 301.75567 | I35: =G35+H35 -> 5583.3864 | K35: 6886.3397 | L35: 364.91163 | M35: =K35+L35 -> 7251.2514 | O35: 154241.73 | P35: 1646.147 | Q35: =O35+P35 -> 155887.88 | S35: =(E35+I35)/Q35 -> 0.95348419 | T35: =M35/Q35 -> 0.046515812 | V35: =(C35+G35)/Q35 -> 0.94526523 | W35: =(D35+H35)/Q35 -> 0.0082189543 | X35: =K35/Q35 -> 0.044174952 | Y35: =L35/Q35 -> 0.0023408595
B36: 44440 | C36: 137045.2 | D36: 928.7554 | E36: =C36+D36 -> 137973.96 | G36: =4355.1715+937.7245 -> 5292.896 | H36: =186.2257+89.8605 -> 276.0862 | I36: =G36+H36 -> 5568.9822 | K36: 6646.6646 | L36: 324.2812 | M36: =K36+L36 -> 6970.9458 | O36: 148979.38 | P36: 1541.994 | Q36: =O36+P36 -> 150521.37 | S36: =(E36+I36)/Q36 -> 0.95363825 | T36: =M36/Q36 -> 0.046312 | V36: =(C36+G36)/Q36 -> 0.9456338 | W36: =(D36+H36)/Q36 -> 0.0080044553 | X36: =K36/Q36 -> 0.044157614 | Y36: =L36/Q36 -> 0.0021543864
B37: 44470 | C37: 141694.61 | D37: 858.2874 | E37: =C37+D37 -> 142552.9 | G37: =4734.6159+918.8488 -> 5653.4647 | H37: =195.6931+80.9342 -> 276.6273 | I37: =G37+H37 -> 5930.092 | K37: 6816.5336 | L37: 328.3873 | M37: =K37+L37 -> 7144.9209 | O37: 154159.17 | P37: 1463.138 | Q37: =O37+P37 -> 155622.3 | S37: =(E37+I37)/Q37 -> 0.9541241 | T37: =M37/Q37 -> 0.045911933 | V37: =(C37+G37)/Q37 -> 0.94683135 | W37: =(D37+H37)/Q37 -> 0.0072927509 | X37: =K37/Q37 -> 0.043801778 | Y37: =L37/Q37 -> 0.0021101557
B38: 44501 | C38: ='[21]Consumo Diário'!$C$42 -> 136942.6 | D38: ='[21]Consumo Diário'!$D$42 -> 864.0848 | E38: =C38+D38 -> 137806.69 | G38: =O38-C38-K38 -> 5158.9242 | H38: =P38-D38-L38 -> 276.65422 | I38: =G38+H38 -> 5435.5785 | K38: ='[21]Consumo Diário'!$EI$42 -> 6599.6263 | L38: ='[21]Consumo Diário'!$EJ$42 -> 292.52498 | M38: =K38+L38 -> 6892.1512 | O38: ='[21]Consumo Diário'!$ED$42 -> 148701.15 | P38: ='[21]Consumo Diário'!$EE$42 -> 1433.264 | Q38: =O38+P38 -> 150134.42 | S38: =(E38+I38)/Q38 -> 0.95409346 | T38: =M38/Q38 -> 0.045906538 | V38: =(C38+G38)/Q38 -> 0.94649534 | W38: =(D38+H38)/Q38 -> 0.007598118 | X38: =K38/Q38 -> 0.043958117 | Y38: =L38/Q38 -> 0.0019484206
B39: 44531 | C39: ='[22]Consumo Diário'!$C$42 -> 140433.22 | D39: ='[22]Consumo Diário'!$D$42 -> 1027.0577 | E39: =C39+D39 -> 141460.28 | G39: =O39-C39-K39 -> 5268.354 | H39: =P39-D39-L39 -> 294.22209 | I39: =G39+H39 -> 5562.576 | K39: ='[22]Consumo Diário'!$EI$42 -> 7027.6148 | L39: ='[22]Consumo Diário'!$EJ$42 -> 352.98321 | M39: =K39+L39 -> 7380.5981 | O39: ='[22]Consumo Diário'!$ED$42 -> 152729.19 | P39: ='[22]Consumo Diário'!$EE$42 -> 1674.263 | Q39: =O39+P39 -> 154403.45 | S39: =(E39+I39)/Q39 -> 0.95219927 | T39: =M39/Q39 -> 0.047800733 | V39: =(C39+G39)/Q39 -> 0.94364195 | W39: =(D39+H39)/Q39 -> 0.0085573204 | X39: =K39/Q39 -> 0.045514623 | Y39: =L39/Q39 -> 0.0022861096
B40: 44562 | C40: ='[23]Consumo Diário'!$C$42 -> 137269.28 | D40: ='[23]Consumo Diário'!$D$42 -> 933.5832 | E40: =C40+D40 -> 138202.86 | G40: =O40-C40-K40 -> 5242.8355 | H40: =P40-D40-L40 -> 287.55232 | I40: =G40+H40 -> 5530.3878 | K40: ='[23]Consumo Diário'!$EI$42 -> 7160.483 | L40: ='[23]Consumo Diário'!$EJ$42 -> 344.09248 | M40: =K40+L40 -> 7504.5755 | O40: ='[23]Consumo Diário'!$ED$42 -> 149672.6 | P40: ='[23]Consumo Diário'!$EE$42 -> 1565.228 | Q40: =O40+P40 -> 151237.83 | S40: =(E40+I40)/Q40 -> 0.95037898 | T40: =M40/Q40 -> 0.049621022 | V40: =(C40+G40)/Q40 -> 0.9423047 | W40: =(D40+H40)/Q40 -> 0.0080742732 | X40: =K40/Q40 -> 0.047345847 | Y40: =L40/Q40 -> 0.0022751747
B41: 44593 | C41: ='[24]Consumo Diário'!$C$42 -> 127696.46 | D41: ='[24]Consumo Diário'!$D$42 -> 847.3136 | E41: =C41+D41 -> 128543.78 | G41: =O41-C41-K41 -> 4730.5633 | H41: =P41-D41-L41 -> 280.64253 | I41: =G41+H41 -> 5011.2058 | K41: ='[24]Consumo Diário'!$EI$42 -> 6280.5941 | L41: ='[24]Consumo Diário'!$EJ$42 -> 365.58287 | M41: =K41+L41 -> 6646.177 | O41: ='[24]Consumo Diário'!$ED$42 -> 138707.62 | P41: ='[24]Consumo Diário'!$EE$42 -> 1493.539 | Q41: =O41+P41 -> 140201.16 | S41: =(E41+I41)/Q41 -> 0.95259542 | T41: =M41/Q41 -> 0.047404579 | V41: =(C41+G41)/Q41 -> 0.94455015 | W41: =(D41+H41)/Q41 -> 0.0080452696 | X41: =K41/Q41 -> 0.04479702 | Y41: =L41/Q41 -> 0.0026075595
B42: 44621 | C42: ='[25]Consumo Diário'!$C$42 -> 138476.43 | D42: ='[25]Consumo Diário'!$D$42 -> 984.5133 | E42: =C42+D42 -> 139460.94 | G42: =O42-C42-K42 -> 5280.3864 | H42: =P42-D42-L42 -> 312.76599 | I42: =G42+H42 -> 5593.1523 | K42: ='[25]Consumo Diário'!$EI$42 -> 7054.6794 | L42: ='[25]Consumo Diário'!$EJ$42 -> 379.72671 | M42: =K42+L42 -> 7434.4062 | O42: ='[25]Consumo Diário'!$ED$42 -> 150811.49 | P42: ='[25]Consumo Diário'!$EE$42 -> 1677.006 | Q42: =O42+P42 -> 152488.5 | S42: =(E42+I42)/Q42 -> 0.95124612 | T42: =M42/Q42 -> 0.048753882 | V42: =(C42+G42)/Q42 -> 0.94273873 | W42: =(D42+H42)/Q42 -> 0.0085073911 | X42: =K42/Q42 -> 0.046263683 | Y42: =L42/Q42 -> 0.0024901991
B43: 44652 | C43: ='[26]Consumo Diário'!$C$42 -> 133770.37 | D43: ='[26]Consumo Diário'!$D$42 -> 805.9326 | E43: =C43+D43 -> 134576.3 | G43: =O43-C43-K43 -> 5039.086 | H43: =P43-D43-L43 -> 258.10846 | I43: =G43+H43 -> 5297.1944 | K43: ='[26]Consumo Diário'!$EI$42 -> 7048.2208 | L43: ='[26]Consumo Diário'!$EJ$42 -> 348.32894 | M43: =K43+L43 -> 7396.5498 | O43: ='[26]Consumo Diário'!$ED$42 -> 145857.68 | P43: ='[26]Consumo Diário'!$EE$42 -> 1412.37 | Q43: =O43+P43 -> 147270.05 | S43: =(E43+I43)/Q43 -> 0.9497756 | T43: =M43/Q43 -> 0.0502244 | V43: =(C43+G43)/Q43 -> 0.9425505 | W43: =(D43+H43)/Q43 -> 0.0072251016 | X43: =K43/Q43 -> 0.04785916 | Y43: =L43/Q43 -> 0.0023652395
B44: 44682 | C44: ='[27]Consumo Diário'!$C$42 -> 131161.7 | D44: ='[27]Consumo Diário'!$D$42 -> 883.3423 | E44: =C44+D44 -> 132045.04 | G44: =O44-C44-K44 -> 4945.803 | H44: =P44-D44-L44 -> 257.09754 | I44: =G44+H44 -> 5202.9006 | K44: ='[27]Consumo Diário'!$EI$42 -> 6795.3188 | L44: ='[27]Consumo Diário'!$EJ$42 -> 342.34816 | M44: =K44+L44 -> 7137.6669 | O44: ='[27]Consumo Diário'!$ED$42 -> 142902.82 | P44: ='[27]Consumo Diário'!$EE$42 -> 1482.788 | Q44: =O44+P44 -> 144385.61 | S44: =(E44+I44)/Q44 -> 0.95056525 | T44: =M44/Q44 -> 0.049434755 | V44: =(C44+G44)/Q44 -> 0.94266668 | W44: =(D44+H44)/Q44 -> 0.0078985702 | X44: =K44/Q44 -> 0.047063686 | Y44: =L44/Q44 -> 0.0023710685
B45: 44713 | C45: ='[28]Consumo Diário'!$C$42 -> 133737.76 | D45: ='[28]Consumo Diário'!$D$42 -> 929.9089 | E45: =C45+D45 -> 134667.67 | G45: =O45-C45-K45 -> 5665.2149 | H45: =P45-D45-L45 -> 281.00693 | I45: =G45+H45 -> 5946.2218 | K45: ='[28]Consumo Diário'!$EI$42 -> 6799.4281 | L45: ='[28]Consumo Diário'!$EJ$42 -> 351.04817 | M45: =K45+L45 -> 7150.4763 | O45: ='[28]Consumo Diário'!$ED$42 -> 146202.4 | P45: ='[28]Consumo Diário'!$EE$42 -> 1561.964 | Q45: =O45+P45 -> 147764.37 | S45: =(E45+I45)/Q45 -> 0.95160893 | T45: =M45/Q45 -> 0.048391073 | V45: =(C45+G45)/Q45 -> 0.94341402 | W45: =(D45+H45)/Q45 -> 0.0081949109 | X45: =K45/Q45 -> 0.046015343 | Y45: =L45/Q45 -> 0.0023757295
B46: 44743 | C46: ='[29]Consumo Diário'!$C$42 -> 140204.51 | D46: ='[29]Consumo Diário'!$D$42 -> 875.6943 | E46: =C46+D46 -> 141080.2 | G46: =O46-C46-K46 -> 5963.5487 | H46: =P46-D46-L46 -> 314.191 | I46: =G46+H46 -> 6277.7397 | K46: ='[29]Consumo Diário'!$EI$42 -> 6877.8075 | L46: ='[29]Consumo Diário'!$EJ$42 -> 340.4347 | M46: =K46+L46 -> 7218.2422 | O46: ='[29]Consumo Diário'!$ED$42 -> 153045.87 | P46: ='[29]Consumo Diário'!$EE$42 -> 1530.32 | Q46: =O46+P46 -> 154576.19 | S46: =(E46+I46)/Q46 -> 0.95330301 | T46: =M46/Q46 -> 0.046696987 | V46: =(C46+G46)/Q46 -> 0.94560529 | W46: =(D46+H46)/Q46 -> 0.0076977271 | X46: =K46/Q46 -> 0.044494612 | Y46: =L46/Q46 -> 0.0022023748
B47: 44774 | C47: ='[30]Consumo Diário'!$C$42 -> 128876.9 | D47: ='[30]Consumo Diário'!$D$42 -> 1004.6584 | E47: =C47+D47 -> 129881.56 | G47: =O47-C47-K47 -> 6123.2936 | H47: =P47-D47-L47 -> 337.24139 | I47: =G47+H47 -> 6460.535 | K47: ='[30]Consumo Diário'!$EI$42 -> 6479.9283 | L47: ='[30]Consumo Diário'!$EJ$42 -> 364.24621 | M47: =K47+L47 -> 6844.1745 | O47: ='[30]Consumo Diário'!$ED$42 -> 141480.12 | P47: ='[30]Consumo Diário'!$EE$42 -> 1706.146 | Q47: =O47+P47 -> 143186.27 | S47: =(E47+I47)/Q47 -> 0.9522009 | T47: =M47/Q47 -> 0.047799099 | V47: =(C47+G47)/Q47 -> 0.94282919 | W47: =(D47+H47)/Q47 -> 0.0093717074 | X47: =K47/Q47 -> 0.045255236 | Y47: =L47/Q47 -> 0.0025438628
B48: 44805 | C48: ='[31]Consumo Diário'!$C$42 -> 129832.68 | D48: ='[31]Consumo Diário'!$D$42 -> 987.6476 | E48: =C48+D48 -> 130820.33 | G48: =O48-C48-K48 -> 5452.6681 | H48: =P48-D48-L48 -> 261.29373 | I48: =G48+H48 -> 5713.9618 | K48: ='[31]Consumo Diário'!$EI$42 -> 6162.3594 | L48: ='[31]Consumo Diário'!$EJ$42 -> 368.48867 | M48: =K48+L48 -> 6530.8481 | O48: ='[31]Consumo Diário'!$ED$42 -> 141447.71 | P48: ='[31]Consumo Diário'!$EE$42 -> 1617.43 | Q48: =O48+P48 -> 143065.14 | S48: =(E48+I48)/Q48 -> 0.95435053 | T48: =M48/Q48 -> 0.045649472 | V48: =(C48+G48)/Q48 -> 0.94562065 | W48: =(D48+H48)/Q48 -> 0.0087298789 | X48: =K48/Q48 -> 0.043073802 | Y48: =L48/Q48 -> 0.0025756706
B49: 44835 | C49: ='[32]Consumo Diário'!$C$42 -> 140033.51 | D49: ='[32]Consumo Diário'!$D$42 -> 912.8292 | E49: =C49+D49 -> 140946.34 | G49: =O49-C49-K49 -> 5686.876 | H49: =P49-D49-L49 -> 283.04331 | I49: =G49+H49 -> 5969.9193 | K49: ='[32]Consumo Diário'!$EI$42 -> 6868.3652 | L49: ='[32]Consumo Diário'!$EJ$42 -> 331.77249 | M49: =K49+L49 -> 7200.1377 | O49: ='[32]Consumo Diário'!$ED$42 -> 152588.75 | P49: ='[32]Consumo Diário'!$EE$42 -> 1527.645 | Q49: =O49+P49 -> 154116.4 | S49: =(E49+I49)/Q49 -> 0.95328117 | T49: =M49/Q49 -> 0.046718829 | V49: =(C49+G49)/Q49 -> 0.94552163 | W49: =(D49+H49)/Q49 -> 0.0077595409 | X49: =K49/Q49 -> 0.044566089 | Y49: =L49/Q49 -> 0.0021527397
B50: 44866 | C50: ='[33]Consumo Diário'!$C$42 -> 133432.29 | D50: ='[33]Consumo Diário'!$D$42 -> 915.7512 | E50: =C50+D50 -> 134348.04 | G50: =O50-C50-K50 -> 5306.2404 | H50: =P50-D50-L50 -> 270.07624 | I50: =G50+H50 -> 5576.3167 | K50: ='[33]Consumo Diário'!$EU$42 -> 6766.2187 | L50: ='[33]Consumo Diário'!$EV$42 -> 315.22756 | M50: =K50+L50 -> 7081.4462 | O50: ='[33]Consumo Diário'!$EP$42 -> 145504.75 | P50: ='[33]Consumo Diário'!$EQ$42 -> 1501.055 | Q50: =O50+P50 -> 147005.8 | S50: =(E50+I50)/Q50 -> 0.9518288 | T50: =M50/Q50 -> 0.048171202 | V50: =(C50+G50)/Q50 -> 0.94376226 | W50: =(D50+H50)/Q50 -> 0.0080665348 | X50: =K50/Q50 -> 0.046026881 | Y50: =L50/Q50 -> 0.0021443205
B51: 44896 | C51: ='[34]Consumo Diário'!$C$42 -> 136878.71 | D51: ='[34]Consumo Diário'!$D$42 -> 986.6578 | E51: =C51+D51 -> 137865.37 | G51: =O51-C51-K51 -> 5434.2688 | H51: =P51-D51-L51 -> 293.27431 | I51: =G51+H51 -> 5727.5431 | K51: ='[34]Consumo Diário'!$EU$42 -> 6977.8304 | L51: ='[34]Consumo Diário'!$EV$42 -> 359.63589 | M51: =K51+L51 -> 7337.4663 | O51: ='[34]Consumo Diário'!$EP$42 -> 149290.81 | P51: ='[34]Consumo Diário'!$EQ$42 -> 1639.568 | Q51: =O51+P51 -> 150930.38 | S51: =(E51+I51)/Q51 -> 0.95138509 | T51: =M51/Q51 -> 0.048614906 | V51: =(C51+G51)/Q51 -> 0.94290481 | W51: =(D51+H51)/Q51 -> 0.0084802815 | X51: =K51/Q51 -> 0.046232113 | Y51: =L51/Q51 -> 0.0023827933
B52: 44927 | C52: ='[35]Consumo Diário'!$C$42 -> 131386.78 | D52: ='[35]Consumo Diário'!$D$42 -> 977.7568 | E52: =C52+D52 -> 132364.54 | G52: =O52-C52-K52 -> 5412.0796 | H52: =P52-D52-L52 -> 298.06957 | I52: =G52+H52 -> 5710.1491 | K52: ='[35]Consumo Diário'!$EU$42 -> 6888.6673 | L52: ='[35]Consumo Diário'!$EV$42 -> 374.03563 | M52: =K52+L52 -> 7262.703 | O52: ='[35]Consumo Diário'!$EP$42 -> 143687.53 | P52: ='[35]Consumo Diário'!$EQ$42 -> 1649.862 | Q52: =O52+P52 -> 145337.39 | S52: =(E52+I52)/Q52 -> 0.95002867 | T52: =M52/Q52 -> 0.049971331 | V52: =(C52+G52)/Q52 -> 0.94125029 | W52: =(D52+H52)/Q52 -> 0.0087783767 | X52: =K52/Q52 -> 0.047397764 | Y52: =L52/Q52 -> 0.0025735678
B53: 44958 | C53: ='[36]Consumo Diário'!$C$42 -> 118667.74 | D53: ='[36]Consumo Diário'!$D$42 -> 822.5535 | E53: =C53+D53 -> 119490.29 | G53: =O53-C53-K53 -> 4749.7327 | H53: =P53-D53-L53 -> 254.13334 | I53: =G53+H53 -> 5003.866 | K53: ='[36]Consumo Diário'!$EU$42 -> 6514.3789 | L53: ='[36]Consumo Diário'!$EV$42 -> 329.60816 | M53: =K53+L53 -> 6843.9871 | O53: ='[36]Consumo Diário'!$EP$42 -> 129931.85 | P53: ='[36]Consumo Diário'!$EQ$42 -> 1406.295 | Q53: =O53+P53 -> 131338.15 | S53: =(E53+I53)/Q53 -> 0.94789033 | T53: =M53/Q53 -> 0.052109667 | V53: =(C53+G53)/Q53 -> 0.93969251 | W53: =(D53+H53)/Q53 -> 0.0081978227 | X53: =K53/Q53 -> 0.049600052 | Y53: =L53/Q53 -> 0.0025096148
B54: 44986 | C54: ='[37]Consumo Diário'!$C$42 -> 118620.55 | D54: ='[37]Consumo Diário'!$D$42 -> 1037.603 | E54: =C54+D54 -> 119658.15 | G54: =O54-C54-K54 -> 4422.4405 | H54: =P54-D54-L54 -> 289.29922 | I54: =G54+H54 -> 4711.7397 | K54: ='[37]Consumo Diário'!$EU$42 -> 7115.9143 | L54: ='[37]Consumo Diário'!$EV$42 -> 401.82775 | M54: =K54+L54 -> 7517.7421 | O54: ='[37]Consumo Diário'!$EP$42 -> 130158.9 | P54: ='[37]Consumo Diário'!$EQ$42 -> 1728.73 | Q54: =O54+P54 -> 131887.63 | S54: =(E54+I54)/Q54 -> 0.94299889 | T54: =M54/Q54 -> 0.057001115 | V54: =(C54+G54)/Q54 -> 0.93293803 | W54: =(D54+H54)/Q54 -> 0.010060854 | X54: =K54/Q54 -> 0.053954371 | Y54: =L54/Q54 -> 0.0030467432
B55: 45017 | C55: ='[38]Consumo Diário'!$C$42 -> 127990.86 | D55: ='[38]Consumo Diário'!$D$42 -> 774.7566 | E55: =C55+D55 -> 128765.62 | G55: =O55-C55-K55 -> 5618.3182 | H55: =P55-D55-L55 -> 239.42949 | I55: =G55+H55 -> 5857.7477 | K55: ='[38]Consumo Diário'!$EU$42 -> 6906.4152 | L55: ='[38]Consumo Diário'!$EV$42 -> 300.96691 | M55: =K55+L55 -> 7207.3821 | O55: ='[38]Consumo Diário'!$EP$42 -> 140515.59 | P55: ='[38]Consumo Diário'!$EQ$42 -> 1315.153 | Q55: =O55+P55 -> 141830.75 | S55: =(E55+I55)/Q55 -> 0.94918322 | T55: =M55/Q55 -> 0.050816781 | V55: =(C55+G55)/Q55 -> 0.94203254 | W55: =(D55+H55)/Q55 -> 0.0071506785 | X55: =K55/Q55 -> 0.048694767 | Y55: =L55/Q55 -> 0.0021220146
B56: 45047 | C56: ='[39]Consumo Diário'!$C$42 -> 134270.04 | D56: ='[39]Consumo Diário'!$D$42 -> 1001.9914 | E56: =C56+D56 -> 135272.03 | G56: =O56-C56-K56 -> 6312.3807 | H56: =P56-D56-L56 -> 289.38687 | I56: =G56+H56 -> 6601.7675 | K56: ='[39]Consumo Diário'!$EU$42 -> 7229.2995 | L56: ='[39]Consumo Diário'!$EV$42 -> 347.39073 | M56: =K56+L56 -> 7576.6903 | O56: ='[39]Consumo Diário'!$EP$42 -> 147811.72 | P56: ='[39]Consumo Diário'!$EQ$42 -> 1638.769 | Q56: =O56+P56 -> 149450.49 | S56: =(E56+I56)/Q56 -> 0.94930301 | T56: =M56/Q56 -> 0.050696991 | V56: =(C56+G56)/Q56 -> 0.94066217 | W56: =(D56+H56)/Q56 -> 0.0086408432 | X56: =K56/Q56 -> 0.048372538 | Y56: =L56/Q56 -> 0.0023244536
B57: 45078 | C57: ='[40]Consumo Diário'!$C$42 -> 127479.29 | D57: ='[40]Consumo Diário'!$D$42 -> 905.2119 | E57: =C57+D57 -> 128384.5 | G57: =O57-C57-K57 -> 5847.694 | H57: =P57-D57-L57 -> 278.07018 | I57: =G57+H57 -> 6125.7642 | K57: ='[40]Consumo Diário'!$EU$42 -> 7055.3419 | L57: ='[40]Consumo Diário'!$EV$42 -> 350.23292 | M57: =K57+L57 -> 7405.5748 | O57: ='[40]Consumo Diário'!$EP$42 -> 140382.32 | P57: ='[40]Consumo Diário'!$EQ$42 -> 1533.515 | Q57: =O57+P57 -> 141915.84 | S57: =(E57+I57)/Q57 -> 0.94781714 | T57: =M57/Q57 -> 0.052182864 | V57: =(C57+G57)/Q57 -> 0.93947922 | W57: =(D57+H57)/Q57 -> 0.0083379143 | X57: =K57/Q57 -> 0.049714972 | Y57: =L57/Q57 -> 0.0024678918
B58: 45108 | C58: ='[41]Consumo Diário'!$C$42 -> 131535.22 | D58: ='[41]Consumo Diário'!$D$42 -> 925.6256 | E58: =C58+D58 -> 132460.84 | G58: =O58-C58-K58 -> 6383.016 | H58: =P58-D58-L58 -> 272.59675 | I58: =G58+H58 -> 6655.6128 | K58: ='[41]Consumo Diário'!$EU$42 -> 6918.4971 | L58: ='[41]Consumo Diário'!$EV$42 -> 302.54365 | M58: =K58+L58 -> 7221.0407 | O58: ='[41]Consumo Diário'!$EP$42 -> 144836.73 | P58: ='[41]Consumo Diário'!$EQ$42 -> 1500.766 | Q58: =O58+P58 -> 146337.5 | S58: =(E58+I58)/Q58 -> 0.95065488 | T58: =M58/Q58 -> 0.049345115 | V58: =(C58+G58)/Q58 -> 0.94246681 | W58: =(D58+H58)/Q58 -> 0.0081880746 | X58: =K58/Q58 -> 0.047277678 | Y58: =L58/Q58 -> 0.0020674377
B59: 45139 | C59: ='[42]Consumo Diário'!$C$42 -> 123349.25 | D59: ='[42]Consumo Diário'!$D$42 -> 12838.795 | E59: =C59+D59 -> 136188.04 | G59: =O59-C59-K59 -> 6388.0289 | H59: =P59-D59-L59 -> 680.03439 | I59: =G59+H59 -> 7068.0633 | K59: ='[42]Consumo Diário'!$EU$42 -> 6623.1917 | L59: ='[42]Consumo Diário'!$EV$42 -> 700.93551 | M59: =K59+L59 -> 7324.1272 | O59: ='[42]Consumo Diário'!$EP$42 -> 136360.47 | P59: ='[42]Consumo Diário'!$EQ$42 -> 14219.765 | Q59: =O59+P59 -> 150580.23 | S59: =(E59+I59)/Q59 -> 0.95136063 | T59: =M59/Q59 -> 0.048639366 | V59: =(C59+G59)/Q59 -> 0.86158239 | W59: =(D59+H59)/Q59 -> 0.089778247 | X59: =K59/Q59 -> 0.043984469 | Y59: =L59/Q59 -> 0.0046548972
B60: 45170 | C60: ='[43]Consumo Diário'!$C$42 -> 119003.61 | D60: ='[43]Consumo Diário'!$D$42 -> 10928.943 | E60: =C60+D60 -> 129932.56 | G60: =O60-C60-K60 -> 5909.9191 | H60: =P60-D60-L60 -> 539.00478 | I60: =G60+H60 -> 6448.9239 | K60: ='[43]Consumo Diário'!$EU$42 -> 6717.4429 | L60: ='[43]Consumo Diário'!$EV$42 -> 636.23902 | M60: =K60+L60 -> 7353.6819 | O60: ='[43]Consumo Diário'!$EP$42 -> 131630.98 | P60: ='[43]Consumo Diário'!$EQ$42 -> 12104.187 | Q60: =O60+P60 -> 143735.16 | S60: =(E60+I60)/Q60 -> 0.94883867 | T60: =M60/Q60 -> 0.051161329 | V60: =(C60+G60)/Q60 -> 0.86905341 | W60: =(D60+H60)/Q60 -> 0.079785265 | X60: =K60/Q60 -> 0.046734862 | Y60: =L60/Q60 -> 0.0044264675
B61: 45200 | C61: ='[44]Consumo Diário'!$C$42 -> 129880.49 | D61: ='[44]Consumo Diário'!$D$42 -> 11927.912 | E61: =C61+D61 -> 141808.4 | G61: =O61-C61-K61 -> 5941.1817 | H61: =P61-D61-L61 -> 698.46143 | I61: =G61+H61 -> 6639.6431 | K61: ='[44]Consumo Diário'!$EU$42 -> 6354.107 | L61: ='[44]Consumo Diário'!$EV$42 -> 453.55977 | M61: =K61+L61 -> 6807.6668 | O61: ='[44]Consumo Diário'!$EP$42 -> 142175.78 | P61: ='[44]Consumo Diário'!$EQ$42 -> 13079.933 | Q61: =O61+P61 -> 155255.71 | S61: =(E61+I61)/Q61 -> 0.95615191 | T61: =M61/Q61 -> 0.043848093 | V61: =(C61+G61)/Q61 -> 0.8748256 | W61: =(D61+H61)/Q61 -> 0.081326305 | X61: =K61/Q61 -> 0.04092672 | Y61: =L61/Q61 -> 0.0029213725
B62: 45231 | C62: ='[45]Consumo Diário'!$C$42 -> 113205.37 | D62: ='[45]Consumo Diário'!$D$42 -> 9885.3035 | E62: =C62+D62 -> 123090.68 | G62: =O62-C62-K62 -> 4750.3714 | H62: =P62-D62-L62 -> 471.49624 | I62: =G62+H62 -> 5221.8677 | K62: ='[45]Consumo Diário'!$EU$42 -> 6064.508 | L62: ='[45]Consumo Diário'!$EV$42 -> 517.85626 | M62: =K62+L62 -> 6582.3642 | O62: ='[45]Consumo Diário'!$EP$42 -> 124020.25 | P62: ='[45]Consumo Diário'!$EQ$42 -> 10874.656 | Q62: =O62+P62 -> 134894.91 | S62: =(E62+I62)/Q62 -> 0.95120376 | T62: =M62/Q62 -> 0.048796239 | V62: =(C62+G62)/Q62 -> 0.87442696 | W62: =(D62+H62)/Q62 -> 0.076776802 | X62: =K62/Q62 -> 0.044957278 | Y62: =L62/Q62 -> 0.0038389607
B63: 45261 | C63: ='[46]Consumo Diário'!$C$42 -> 127562.62 | D63: ='[46]Consumo Diário'!$D$42 -> 10977.829 | E63: =C63+D63 -> 138540.45 | G63: =O63-C63-K63 -> 4680.011 | H63: =P63-D63-L63 -> 409.88071 | I63: =G63+H63 -> 5089.8917 | K63: ='[46]Consumo Diário'!$EU$42 -> 6975.9234 | L63: ='[46]Consumo Diário'!$EV$42 -> 613.51809 | M63: =K63+L63 -> 7589.4415 | O63: ='[46]Consumo Diário'!$EP$42 -> 139218.55 | P63: ='[46]Consumo Diário'!$EQ$42 -> 12001.228 | Q63: =O63+P63 -> 151219.78 | S63: =(E63+I63)/Q63 -> 0.94981185 | T63: =M63/Q63 -> 0.050188154 | V63: =(C63+G63)/Q63 -> 0.87450616 | W63: =(D63+H63)/Q63 -> 0.075305691 | X63: =K63/Q63 -> 0.046131025 | Y63: =L63/Q63 -> 0.0040571286
B64: 45292 | C64: ='[47]Consumo Diário'!$C$39 -> 140815.81 | E64: =C64+D64 -> 140815.81 | G64: =O64-C64-K64 -> 5218.6114 | H64: =P64-D64-L64 -> 0 | I64: =G64+H64 -> 5218.6114 | K64: ='[47]Consumo Diário'!$BA$39 -> 7645.5791 | M64: =K64+L64 -> 7645.5791 | O64: ='[47]Consumo Diário'!$AY$39 -> 153680.01 | Q64: =O64+P64 -> 153680.01 | S64: =(E64+I64)/Q64 -> 0.95025001 | T64: =M64/Q64 -> 0.049749993 | V64: =(C64+G64)/Q64 -> 0.95025001 | X64: =K64/Q64 -> 0.049749993
B65: 45323 | C65: ='[48]Consumo Diário'!$C$39 -> 130989.88 | E65: =C65+D65 -> 130989.88 | G65: =O65-C65-K65 -> 4881.6665 | H65: =P65-D65-L65 -> 0 | I65: =G65+H65 -> 4881.6665 | K65: ='[48]Consumo Diário'!$BA$39 -> 7047.6051 | M65: =K65+L65 -> 7047.6051 | O65: ='[48]Consumo Diário'!$AY$39 -> 142919.15 | Q65: =O65+P65 -> 142919.15 | S65: =(E65+I65)/Q65 -> 0.95068817 | T65: =M65/Q65 -> 0.049311833 | V65: =(C65+G65)/Q65 -> 0.95068817 | X65: =K65/Q65 -> 0.049311833
B66: 45352 | C66: ='[49]Consumo Diário'!$C$39 -> 141733.32 | E66: =C66+D66 -> 141733.32 | G66: =O66-C66-K66 -> 5426.6469 | H66: =P66-D66-L66 -> 0 | I66: =G66+H66 -> 5426.6469 | K66: ='[49]Consumo Diário'!$BA$39 -> 7486.5037 | M66: =K66+L66 -> 7486.5037 | O66: ='[49]Consumo Diário'!$AY$39 -> 154646.47 | Q66: =O66+P66 -> 154646.47 | S66: =(E66+I66)/Q66 -> 0.95158956 | T66: =M66/Q66 -> 0.048410441 | V66: =(C66+G66)/Q66 -> 0.95158956 | X66: =K66/Q66 -> 0.048410441
B67: 45383 | C67: ='[50]Consumo Diário'!$C$39 -> 131029.28 | E67: =C67+D67 -> 131029.28 | G67: =O67-C67-K67 -> 4883.1966 | H67: =P67-D67-L67 -> 0 | I67: =G67+H67 -> 4883.1966 | K67: ='[50]Consumo Diário'!$BA$39 -> 6909.4217 | M67: =K67+L67 -> 6909.4217 | O67: ='[50]Consumo Diário'!$AY$39 -> 142821.9 | Q67: =O67+P67 -> 142821.9 | S67: =(E67+I67)/Q67 -> 0.95162211 | T67: =M67/Q67 -> 0.048377888 | V67: =(C67+G67)/Q67 -> 0.95162211 | X67: =K67/Q67 -> 0.048377888
B68: 45413 | C68: ='[51]Consumo Diário'!$C$39 -> 135422.96 | E68: =C68+D68 -> 135422.96 | G68: =O68-C68-K68 -> 4934.3622 | H68: =P68-D68-L68 -> 0 | I68: =G68+H68 -> 4934.3622 | K68: ='[51]Consumo Diário'!$BA$39 -> 6751.1937 | M68: =K68+L68 -> 6751.1937 | O68: ='[51]Consumo Diário'!$AY$39 -> 147108.51 | Q68: =O68+P68 -> 147108.51 | S68: =(E68+I68)/Q68 -> 0.95410739 | T68: =M68/Q68 -> 0.045892611 | V68: =(C68+G68)/Q68 -> 0.95410739 | X68: =K68/Q68 -> 0.045892611
B69: 45444 | C69: ='[52]Consumo Diário'!$C$39 -> 137757.95 | E69: =C69+D69 -> 137757.95 | G69: =O69-C69-K69 -> 5808.3261 | H69: =P69-D69-L69 -> 0 | I69: =G69+H69 -> 5808.3261 | K69: ='[52]Consumo Diário'!$BA$39 -> 6729.9299 | M69: =K69+L69 -> 6729.9299 | O69: ='[52]Consumo Diário'!$AY$39 -> 150296.21 | Q69: =O69+P69 -> 150296.21 | S69: =(E69+I69)/Q69 -> 0.95522222 | T69: =M69/Q69 -> 0.044777776 | V69: =(C69+G69)/Q69 -> 0.95522222 | X69: =K69/Q69 -> 0.044777776
B71: Média | C71: =AVERAGE(C4:C69) -> 127792.35 | D71: =AVERAGE(D4:D69) -> 1823.1244 | E71: =AVERAGE(E4:E69) -> 129449.74 | G71: =AVERAGE(G4:G69) -> 5104.6827 | H71: =AVERAGE(H4:H69) -> 273.113 | I71: =AVERAGE(I4:I69) -> 5377.7957 | K71: =AVERAGE(K4:K69) -> 6640.9156 | L71: =AVERAGE(L4:L69) -> 332.32512 | M71: =AVERAGE(M4:M69) -> 6943.0293 | O71: =AVERAGE(O4:O69) -> 139537.79 | P71: =AVERAGE(P4:P69) -> 2456.0856 | Q71: =AVERAGE(Q4:Q69) -> 141770.59 | S71: =AVERAGE(S4:S69) -> 0.95078229 | T71: =AVERAGE(T4:T69) -> 0.049217502 | V71: =AVERAGE(V4:V69) -> 0.93722334 | W71: =AVERAGE(W4:W69) -> 0.014914847 | X71: =AVERAGE(X4:X69) -> 0.047073095 | Y71: =AVERAGE(Y4:Y69) -> 0.0023588483
B91: Ajuste Produtividade Andorinha
B92: Atual | C92: Capacidade | D92: Sobra | E92: Uso
B93: 5 | C93: =B93*24*30.5 -> 3660 | D93: =4492/3 -> 1497.3333 | E93: =C93-D93 -> 2162.6667
A94: Ajustada | B94: =C94/(24*30.5) -> 3.5692168 | C94: =D94+E94 -> 2612.6667 | D94: 450 | E94: =E93 -> 2162.6667
D95: Informação Wiclef

Sheet Preços
C4: Preço Contrato (R$) | D4: Data Base | E4: Índice de Reajuste | F4: N° Índice de Reajuste (JAN 2024) | G4: Expectativa Inflação 2024 (Jan 2025) | H4: Preço Reajustado (R$) | I4: Preço Reajustado [SEM PIS/COFINS](R$)
B5: CHESF | C5: 112 | D5: 45017 | E5: IPCA | F5: 1.0363609 | G5: 1.04 | H5: =C5*F5*G5 -> 120.71532 | I5: =H5*0.9075 -> 109.54915 | P5: CHESF
B6: AES | C6: 104.64 | D6: 44136 | E6: IPCA | F6: 1.2615007 | G6: 1.04 | H6: =C6*F6*G6 -> 137.28357 | I6: =H6*0.9075 -> 124.58484
B7: CPFL (Metalurgia) | C7: 128 | D7: 42005 | E7: IPCA | F7: 1.6884231 | G7: 1.04 | H7: =C7*F7*G7 -> 224.76288 | I7: =H7*0.9075 -> 203.97232
B8: AUREN (APE) | C8: 190.2 | D8: 44927 | E8: IPCA | F8: 1.057119 | G8: 1.04 | H8: =C8*F8*G8 -> 209.1066 | I8: =H8*0.9075 -> 189.76424
P18: AES
P34: CPFL
P48: AUREN

Sheet Encargos Mineração
V2: Horas
C3: JAN | D3: FEV | E3: MAR | F3: ABR | G3: MAI | H3: JUN | I3: JUL | J3: AGO | K3: SET | L3: OUT | M3: NOV | N3: DEZ | V3: 2025 | W3: JAN | X3: 66
B4: Horas FP | C4: 678 | D4: 612 | E4: 684 | F4: 660 | G4: 681 | H4: 660 | I4: 675 | J4: 681 | K4: 654 | L4: 675 | M4: 660 | N4: 678 | V4: 2025 | W4: FEV | X4: 60
B5: Horas HP | C5: 66 | D5: 60 | E5: 60 | F5: 60 | G5: 63 | H5: 60 | I5: 69 | J5: 63 | K5: 66 | L5: 69 | M5: 60 | N5: 66 | V5: 2025 | W5: MAR | X5: 60
V6: 2025 | W6: ABR | X6: 60
C7: Demanda Contratada (kW) | F7: Energia (MWMed) | V7: 2025 | W7: MAI | X7: 63
C8: HP | D8: 7090 | F8: HP | G8: 5 | V8: 2025 | W8: JUN | X8: 60
C9: FP | D9: 7090 | F9: FP | G9: 5 | V9: 2025 | W9: JUL | X9: 69
V10: 2025 | W10: AGO | X10: 63
B11: Energia FP | C11: =$G$8*C4 -> 3390 | D11: =$G$8*D4 -> 3060 | E11: =$G$8*E4 -> 3420 | F11: =$G$8*F4 -> 3300 | G11: =$G$8*G4 -> 3405 | H11: =$G$8*H4 -> 3300 | I11: =$G$8*I4 -> 3375 | J11: =$G$8*J4 -> 3405 | ... N11: =$G$8*N4 -> 3390 | V11: 2025 | W11: SET | X11: 66
B12: Energia HP | C12: =$G$9*C5 -> 330 | D12: =$G$9*D5 -> 300 | E12: =$G$9*E5 -> 300 | F12: =$G$9*F5 -> 300 | G12: =$G$9*G5 -> 315 | H12: =$G$9*H5 -> 300 | I12: =$G$9*I5 -> 345 | J12: =$G$9*J5 -> 315 | ... N12: =$G$9*N5 -> 330 | V12: 2025 | W12: OUT | X12: 69
V13: 2025 | W13: NOV | X13: 60
B14: TUSD FIO | V14: 2025 | W14: DEZ | X14: 66
B15: Custo FP | C15: =$D$9*$S$28 -> 136198.9 | D15: =$D$9*$S$28 -> 136198.9 | E15: =$D$9*$S$28 -> 136198.9 | F15: =$D$9*$S$21 -> 105711.9 | G15: =$D$9*$S$21 -> 105711.9 | H15: =$D$9*$S$21 -> 105711.9 | I15: =$D$9*$S$21 -> 105711.9 | J15: =$D$9*$S$21 -> 105711.9 | K15: =$D$9*$S$21 -> 105711.9 | L15: =$D$9*$S$21 -> 105711.9 | M15: =$D$9*$S$21 -> 105711.9 | N15: =$D$9*$S$21 -> 105711.9
B16: Custo HP | C16: =$D$8*$S$29 -> 251482.3 | D16: =$D$8*$S$29 -> 251482.3 | E16: =$D$8*$S$29 -> 251482.3 | F16: =$D$8*$S$22 -> 225958.3 | G16: =$D$8*$S$22 -> 225958.3 | H16: =$D$8*$S$22 -> 225958.3 | I16: =$D$8*$S$22 -> 225958.3 | J16: =$D$8*$S$22 -> 225958.3 | K16: =$D$8*$S$22 -> 225958.3 | L16: =$D$8*$S$22 -> 225958.3 | M16: =$D$8*$S$22 -> 225958.3 | N16: =$D$8*$S$22 -> 225958.3
B18: TUSD Encargos
B19: Custo FP | C19: =C11*$S$30 -> 172110.3 | D19: =D11*$S$30 -> 155356.2 | E19: =E11*$S$30 -> 173633.4 | F19: =F11*$S$23 -> 178464 | G19: =G11*$S$23 -> 184142.4 | H19: =H11*$S$23 -> 178464 | I19: =I11*$S$23 -> 182520 | J19: =J11*$S$23 -> 184142.4 | K19: =K11*$S$23 -> 176841.6 | L19: =L11*$S$23 -> 182520 | M19: =M11*$S$23 -> 178464 | N19: =N11*$S$23 -> 183331.2
B20: Custo HP | C20: =C12*$S$31 -> 16754.1 | D20: =D12*$S$31 -> 15231 | E20: =E12*$S$31 -> 15231 | F20: =F12*$S$24 -> 16224 | G20: =G12*$S$24 -> 17035.2 | H20: =H12*$S$24 -> 16224 | I20: =I12*$S$24 -> 18657.6 | J20: =J12*$S$24 -> 17035.2 | K20: =K12*$S$24 -> 17846.4 | L20: =L12*$S$24 -> 18657.6 | M20: =M12*$S$24 -> 16224 | N20: =N12*$S$24 -> 17846.4 | R20: Valores a Partir de Abril - Reajuste ANUAL COELBA
R21: TUSD - Fio FP | S21: =14.91 -> 14.91 | T21: R$/MW
B22: Consolidado | R22: TUSD - Fio HP | S22: =31.87 -> 31.87 | T22: R$/MW
B23: Mês | C23: JAN | D23: FEV | E23: MAR | F23: ABR | G23: MAI | H23: JUN | I23: JUL | J23: AGO | K23: SET | L23: OUT | M23: NOV | N23: DEZ | R23: Encargos - FP | S23: 54.08 | T23: R$/MWh
B24: TUSD - FIO | C24: =SUM(C15:C16)/SUM(C11:C12) -> 104.21538 | D24: =SUM(D15:D16)/SUM(D11:D12) -> 115.38131 | E24: =SUM(E15:E16)/SUM(E11:E12) -> 104.21538 | F24: =SUM(F15:F16)/SUM(F11:F12) -> 92.130611 | G24: =SUM(G15:G16)/SUM(G11:G12) -> 89.158656 | H24: =SUM(H15:H16)/SUM(H11:H12) -> 92.130611 | I24: =SUM(I15:I16)/SUM(I11:I12) -> 89.158656 | J24: =SUM(J15:J16)/SUM(J11:J12) -> 89.158656 | ... N24: =SUM(N15:N16)/SUM(N11:N12) -> 89.158656 | R24: Encargos - HP | S24: 54.08 | T24: R$/MWh
B25: TUSD - Encargos | C25: =SUM(C19:C20)/SUM(C11:C12) -> 50.77 | D25: =SUM(D19:D20)/SUM(D11:D12) -> 50.77 | E25: =SUM(E19:E20)/SUM(E11:E12) -> 50.77 | F25: =SUM(F19:F20)/SUM(F11:F12) -> 54.08 | G25: =SUM(G19:G20)/SUM(G11:G12) -> 54.08 | H25: =SUM(H19:H20)/SUM(H11:H12) -> 54.08 | I25: =SUM(I19:I20)/SUM(I11:I12) -> 54.08 | J25: =SUM(J19:J20)/SUM(J11:J12) -> 54.08 | ... N25: =SUM(N19:N20)/SUM(N11:N12) -> 54.08
R27: Valores JAN a MAR COELBA
B28: Preço Médio - Trimestral (RESUMO) | R28: TUSD - Fio FP | S28: 19.21 | T28: R$/MW
C29: 1T 2024 | D29: 2T 2024 | E29: 3T 2024 | F29: 4T 2024 | R29: TUSD - Fio HP | S29: 35.47 | T29: R$/MW
B30: TUSD - FIO | C30: =SUM($C$15:$E$16)/SUM($C$11:$E$12) -> 107.68922 | D30: =SUM($F$15:$H$16)/SUM($F$11:$H$12) -> 91.118187 | E30: =SUM($I$15:$K$16)/SUM($I$11:$K$12) -> 90.127772 | F30: =SUM($L$15:$N$16)/SUM($L$11:$N$12) -> 90.127772 | R30: Encargos - FP | S30: 50.77 | T30: R$/MWh
B31: TUSD - Encargos | C31: =SUM($C$19:$E$20)/SUM($C$11:$E$12) -> 50.77 | D31: =SUM($F$19:$H$20)/SUM($F$11:$H$12) -> 54.08 | E31: =SUM($I$19:$K$20)/SUM($I$11:$K$12) -> 54.08 | F31: =SUM($L$19:$N$20)/SUM($L$11:$N$12) -> 54.08 | R31: Encargos - HP | S31: 50.77 | T31: R$/MWh
